{"US":[{"number":"1","trackName":"Calling My Phone","artist":"Lil Tjay","streams":"1362616","url":"https://open.spotify.com/track/5Kskr9LcNYa0tpt5f0ZEJx"},{"number":"2","trackName":"drivers license","artist":"Olivia Rodrigo","streams":"1299468","url":"https://open.spotify.com/track/7lPN2DXiMsVn7XUKtOW1CS"},{"number":"3","trackName":"Good Days","artist":"SZA","streams":"895485","url":"https://open.spotify.com/track/3YJJjQPAbDT7mGpX3WtQ9A"},{"number":"4","trackName":"Save Your Tears","artist":"The Weeknd","streams":"872273","url":"https://open.spotify.com/track/5QO79kh1waicV47BqGRL3g"},{"number":"5","trackName":"Up","artist":"Cardi B","streams":"795573","url":"https://open.spotify.com/track/1M4OcYkxAtu3ErzSgDEfoi"},{"number":"6","trackName":"Streets","artist":"Doja Cat","streams":"752507","url":"https://open.spotify.com/track/60ynsPSSKe6O3sfwRnIBRf"},{"number":"7","trackName":"Blinding Lights","artist":"The Weeknd","streams":"706651","url":"https://open.spotify.com/track/0VjIjW4GlUZAMYd2vXMi3b"},{"number":"8","trackName":"Whoopty","artist":"CJ","streams":"615538","url":"https://open.spotify.com/track/5vGLcdRuSbUhD8ScwsGSdA"},{"number":"9","trackName":"Love Story (Taylor’s Version)","artist":"Taylor Swift","streams":"569377","url":"https://open.spotify.com/track/3CeCwYWvdfXbZLXFhBrbnf"},{"number":"10","trackName":"Mood (feat. iann dior)","artist":"24kGoldn","streams":"554351","url":"https://open.spotify.com/track/3tjFYV6RSFtuktYl3ZtYcq"}],"GB":[{"number":"1","trackName":"drivers license","artist":"Olivia Rodrigo","streams":"427117","url":"https://open.spotify.com/track/7lPN2DXiMsVn7XUKtOW1CS"},{"number":"2","trackName":"Calling My Phone","artist":"Lil Tjay","streams":"418136","url":"https://open.spotify.com/track/5Kskr9LcNYa0tpt5f0ZEJx"},{"number":"3","trackName":"WITHOUT YOU","artist":"The Kid LAROI","streams":"261047","url":"https://open.spotify.com/track/27OeeYzk6klgBh83TSvGMA"},{"number":"4","trackName":"Don't Play","artist":"Anne-Marie","streams":"235253","url":"https://open.spotify.com/track/4I5bvu2KDsrCg0EWHIcvul"},{"number":"5","trackName":"The Business","artist":"Tiësto","streams":"221639","url":"https://open.spotify.com/track/6f3Slt0GbA2bPZlz0aIFXN"},{"number":"6","trackName":"Blinding Lights","artist":"The Weeknd","streams":"196115","url":"https://open.spotify.com/track/0VjIjW4GlUZAMYd2vXMi3b"},{"number":"7","trackName":"Paradise (feat. Dermot Kennedy)","artist":"MEDUZA","streams":"194905","url":"https://open.spotify.com/track/6ft4hAq6yde8jPZY2i5zLr"},{"number":"8","trackName":"Save Your Tears","artist":"The Weeknd","streams":"192303","url":"https://open.spotify.com/track/5QO79kh1waicV47BqGRL3g"},{"number":"9","trackName":"Latest Trends","artist":"A1 x J1","streams":"191726","url":"https://open.spotify.com/track/7pnQ23WgZca9jEfMts9qsR"},{"number":"10","trackName":"Bringing It Back","artist":"Digga D","streams":"182410","url":"https://open.spotify.com/track/3inbZcvbbcwJFgEzZgANwE"}],"AR":[{"number":"1","trackName":"Bandido","artist":"Myke Towers","streams":"351540","url":"https://open.spotify.com/track/1xK1Gg9SxG8fy2Ya373oqb"},{"number":"2","trackName":"L-Gante Rkt","artist":"Papu DJ","streams":"284039","url":"https://open.spotify.com/track/6EHrppRT1Uj4cyShAujxFu"},{"number":"3","trackName":"DÁKITI","artist":"Bad Bunny","streams":"262761","url":"https://open.spotify.com/track/4MzXwWMhyBbmu6hOcLVD49"},{"number":"4","trackName":"BICHOTA","artist":"KAROL G","streams":"259339","url":"https://open.spotify.com/track/7vrJn5hDSXRmdXoR30KgF1"},{"number":"5","trackName":"Hecha Pa' Mi","artist":"Boza","streams":"239201","url":"https://open.spotify.com/track/3VvA1wSxukMLsvXoXtlwWx"},{"number":"6","trackName":"LA NOCHE DE ANOCHE","artist":"Bad Bunny","streams":"239181","url":"https://open.spotify.com/track/2XIc1pqjXV3Cr2BQUGNBck"},{"number":"7","trackName":"Si Me Tomo Una Cerveza","artist":"Migrantes","streams":"231224","url":"https://open.spotify.com/track/3lCbsHaN1wCxyDzcNN2x4N"},{"number":"8","trackName":"Animal","artist":"Maria Becerra","streams":"223772","url":"https://open.spotify.com/track/3OXxCquI8i14EigwILaLx9"},{"number":"9","trackName":"Ropa Cara","artist":"Camilo","streams":"194927","url":"https://open.spotify.com/track/7BIy3EGQhg98CsRdKYHnJC"},{"number":"10","trackName":"BEBÉ","artist":"Camilo","streams":"188464","url":"https://open.spotify.com/track/7D7EH7MGyNHWSkqrszerI1"}],"AT":[{"number":"1","trackName":"Ohne Dich","artist":"KASIMIR1441","streams":"34151","url":"https://open.spotify.com/track/4hSJUp6k7QeHLxU32MrLIU"},{"number":"2","trackName":"drivers license","artist":"Olivia Rodrigo","streams":"30724","url":"https://open.spotify.com/track/7lPN2DXiMsVn7XUKtOW1CS"},{"number":"3","trackName":"WITHOUT YOU","artist":"The Kid LAROI","streams":"23191","url":"https://open.spotify.com/track/27OeeYzk6klgBh83TSvGMA"},{"number":"4","trackName":"Save Your Tears","artist":"The Weeknd","streams":"22251","url":"https://open.spotify.com/track/5QO79kh1waicV47BqGRL3g"},{"number":"5","trackName":"Astronaut In The Ocean","artist":"Masked Wolf","streams":"21102","url":"https://open.spotify.com/track/3VT8hOC5vuDXBsHrR53WFh"},{"number":"6","trackName":"No Comprendo","artist":"Jamule","streams":"19773","url":"https://open.spotify.com/track/5ezbc8nalmV7JqLQQfHwTV"},{"number":"7","trackName":"The Business","artist":"Tiësto","streams":"18689","url":"https://open.spotify.com/track/6f3Slt0GbA2bPZlz0aIFXN"},{"number":"8","trackName":"Mood (feat. iann dior)","artist":"24kGoldn","streams":"18394","url":"https://open.spotify.com/track/3tjFYV6RSFtuktYl3ZtYcq"},{"number":"9","trackName":"All We Got (feat. KIDDO)","artist":"Robin Schulz","streams":"16654","url":"https://open.spotify.com/track/1FP9s72rDYty6mfoOEYKnE"},{"number":"10","trackName":"Blinding Lights","artist":"The Weeknd","streams":"16247","url":"https://open.spotify.com/track/0VjIjW4GlUZAMYd2vXMi3b"}],"AU":[{"number":"1","trackName":"drivers license","artist":"Olivia Rodrigo","streams":"316419","url":"https://open.spotify.com/track/7lPN2DXiMsVn7XUKtOW1CS"},{"number":"2","trackName":"Heat Waves","artist":"Glass Animals","streams":"304978","url":"https://open.spotify.com/track/02MWAaffLxlfxAUY7c5dvx"},{"number":"3","trackName":"Calling My Phone","artist":"Lil Tjay","streams":"264878","url":"https://open.spotify.com/track/5Kskr9LcNYa0tpt5f0ZEJx"},{"number":"4","trackName":"WITHOUT YOU","artist":"The Kid LAROI","streams":"225864","url":"https://open.spotify.com/track/27OeeYzk6klgBh83TSvGMA"},{"number":"5","trackName":"Save Your Tears","artist":"The Weeknd","streams":"158226","url":"https://open.spotify.com/track/5QO79kh1waicV47BqGRL3g"},{"number":"6","trackName":"The Business","artist":"Tiësto","streams":"154644","url":"https://open.spotify.com/track/6f3Slt0GbA2bPZlz0aIFXN"},{"number":"7","trackName":"Good Days","artist":"SZA","streams":"146031","url":"https://open.spotify.com/track/3YJJjQPAbDT7mGpX3WtQ9A"},{"number":"8","trackName":"Mood (feat. iann dior)","artist":"24kGoldn","streams":"141916","url":"https://open.spotify.com/track/3tjFYV6RSFtuktYl3ZtYcq"},{"number":"9","trackName":"SO DONE","artist":"The Kid LAROI","streams":"137848","url":"https://open.spotify.com/track/2gqWRRCXnma9L8xQ1RdemQ"},{"number":"10","trackName":"Streets","artist":"Doja Cat","streams":"134681","url":"https://open.spotify.com/track/60ynsPSSKe6O3sfwRnIBRf"}],"BE":[{"number":"1","trackName":"drivers license","artist":"Olivia Rodrigo","streams":"63136","url":"https://open.spotify.com/track/7lPN2DXiMsVn7XUKtOW1CS"},{"number":"2","trackName":"WITHOUT YOU","artist":"The Kid LAROI","streams":"45662","url":"https://open.spotify.com/track/27OeeYzk6klgBh83TSvGMA"},{"number":"3","trackName":"The Business","artist":"Tiësto","streams":"44661","url":"https://open.spotify.com/track/6f3Slt0GbA2bPZlz0aIFXN"},{"number":"4","trackName":"Fever","artist":"Dua Lipa","streams":"36220","url":"https://open.spotify.com/track/3F1P0QzdXtBz0MXy7KIO5w"},{"number":"5","trackName":"Mood (feat. iann dior)","artist":"24kGoldn","streams":"36137","url":"https://open.spotify.com/track/3tjFYV6RSFtuktYl3ZtYcq"},{"number":"6","trackName":"Save Your Tears","artist":"The Weeknd","streams":"35657","url":"https://open.spotify.com/track/5QO79kh1waicV47BqGRL3g"},{"number":"7","trackName":"Whoopty","artist":"CJ","streams":"31269","url":"https://open.spotify.com/track/5vGLcdRuSbUhD8ScwsGSdA"},{"number":"8","trackName":"you broke me first","artist":"Tate McRae","streams":"29750","url":"https://open.spotify.com/track/45bE4HXI0AwGZXfZtMp8JR"},{"number":"9","trackName":"Paradise (feat. Dermot Kennedy)","artist":"MEDUZA","streams":"29479","url":"https://open.spotify.com/track/6ft4hAq6yde8jPZY2i5zLr"},{"number":"10","trackName":"Blinding Lights","artist":"The Weeknd","streams":"29356","url":"https://open.spotify.com/track/0VjIjW4GlUZAMYd2vXMi3b"}],"BG":[{"number":"1","trackName":"Astronaut In The Ocean","artist":"Masked Wolf","streams":"4090","url":"https://open.spotify.com/track/3VT8hOC5vuDXBsHrR53WFh"},{"number":"2","trackName":"Up","artist":"Cardi B","streams":"3720","url":"https://open.spotify.com/track/1M4OcYkxAtu3ErzSgDEfoi"},{"number":"3","trackName":"Whoopty","artist":"CJ","streams":"3379","url":"https://open.spotify.com/track/5vGLcdRuSbUhD8ScwsGSdA"},{"number":"4","trackName":"Streets","artist":"Doja Cat","streams":"3316","url":"https://open.spotify.com/track/60ynsPSSKe6O3sfwRnIBRf"},{"number":"5","trackName":"drivers license","artist":"Olivia Rodrigo","streams":"3136","url":"https://open.spotify.com/track/7lPN2DXiMsVn7XUKtOW1CS"},{"number":"6","trackName":"Calling My Phone","artist":"Lil Tjay","streams":"2782","url":"https://open.spotify.com/track/5Kskr9LcNYa0tpt5f0ZEJx"},{"number":"7","trackName":"Save Your Tears","artist":"The Weeknd","streams":"2707","url":"https://open.spotify.com/track/5QO79kh1waicV47BqGRL3g"},{"number":"8","trackName":"Chukove","artist":"Marso","streams":"2598","url":"https://open.spotify.com/track/2IxTTLlkB2hSUDn138o8uq"},{"number":"9","trackName":"Blinding Lights","artist":"The Weeknd","streams":"2522","url":"https://open.spotify.com/track/0VjIjW4GlUZAMYd2vXMi3b"},{"number":"10","trackName":"Lemonade (feat. Gunna, Don Toliver & NAV)","artist":"Internet Money","streams":"2516","url":"https://open.spotify.com/track/7hxHWCCAIIxFLCzvDgnQHX"}],"BO":[{"number":"1","trackName":"DÁKITI","artist":"Bad Bunny","streams":"19930","url":"https://open.spotify.com/track/4MzXwWMhyBbmu6hOcLVD49"},{"number":"2","trackName":"Bandido","artist":"Myke Towers","streams":"19844","url":"https://open.spotify.com/track/1xK1Gg9SxG8fy2Ya373oqb"},{"number":"3","trackName":"BICHOTA","artist":"KAROL G","streams":"19434","url":"https://open.spotify.com/track/7vrJn5hDSXRmdXoR30KgF1"},{"number":"4","trackName":"LA NOCHE DE ANOCHE","artist":"Bad Bunny","streams":"17494","url":"https://open.spotify.com/track/2XIc1pqjXV3Cr2BQUGNBck"},{"number":"5","trackName":"Hecha Pa' Mi","artist":"Boza","streams":"15453","url":"https://open.spotify.com/track/3VvA1wSxukMLsvXoXtlwWx"},{"number":"6","trackName":"Reloj","artist":"Rauw Alejandro","streams":"14079","url":"https://open.spotify.com/track/4loQgPwJHocL3dFwLfjb1J"},{"number":"7","trackName":"Hawái","artist":"Maluma","streams":"13148","url":"https://open.spotify.com/track/1yoMvmasuxZfqHEipJhRbp"},{"number":"8","trackName":"Baila Conmigo (with Rauw Alejandro)","artist":"Selena Gomez","streams":"12674","url":"https://open.spotify.com/track/0D75ciM842cdUMKSMfAR9y"},{"number":"9","trackName":"Si Me Tomo Una Cerveza","artist":"Migrantes","streams":"12526","url":"https://open.spotify.com/track/3lCbsHaN1wCxyDzcNN2x4N"},{"number":"10","trackName":"Aquí Abajo","artist":"Christian Nodal","streams":"11345","url":"https://open.spotify.com/track/16ONd70tvWAaLIc6hcLzaG"}],"BR":[{"number":"1","trackName":"Esquema Preferido","artist":"DJ Ivis","streams":"845282","url":"https://open.spotify.com/track/27X3qzgB0Show6qfw5wNOK"},{"number":"2","trackName":"Ele É Ele, Eu Sou Eu","artist":"Wesley Safadão","streams":"834370","url":"https://open.spotify.com/track/7EWXP47VlXKO3r7mNxuWHw"},{"number":"3","trackName":"Facas - Ao Vivo","artist":"Diego & Victor Hugo","streams":"760160","url":"https://open.spotify.com/track/1ere9b9vDw2N3m9d4uiXxa"},{"number":"4","trackName":"Meia Noite (Você tem meu Whatsapp)","artist":"Tarcísio do Acordeon","streams":"646895","url":"https://open.spotify.com/track/6sPBi0qLI6KM3yXX56NxsA"},{"number":"5","trackName":"Alô Ambev (Segue Sua Vida) - Ao Vivo","artist":"Zé Neto & Cristiano","streams":"621531","url":"https://open.spotify.com/track/5m5aY6S9ttfIG157xli2Rs"},{"number":"6","trackName":"Tapão Na Raba","artist":"Raí Saia Rodada","streams":"605767","url":"https://open.spotify.com/track/58pgi1RpcU2fVJsxhm7BIr"},{"number":"7","trackName":"Mds","artist":"Kawe","streams":"605278","url":"https://open.spotify.com/track/0QglpM23kl9ldvVdoYNZwF"},{"number":"8","trackName":"Coração Na Cama","artist":"Hugo & Guilherme","streams":"603123","url":"https://open.spotify.com/track/2nZj5YymF54qhAu7RneVP6"},{"number":"9","trackName":"Recairei - Ao Vivo","artist":"Os Barões Da Pisadinha","streams":"594100","url":"https://open.spotify.com/track/2JTir3y1VuJQmexiTCMcTP"},{"number":"10","trackName":"Lance Individual","artist":"Jorge & Mateus","streams":"581379","url":"https://open.spotify.com/track/7GLWWrk1YlkPYqJK3ynIA0"}],"CA":[{"number":"1","trackName":"Calling My Phone","artist":"Lil Tjay","streams":"254302","url":"https://open.spotify.com/track/5Kskr9LcNYa0tpt5f0ZEJx"},{"number":"2","trackName":"drivers license","artist":"Olivia Rodrigo","streams":"206384","url":"https://open.spotify.com/track/7lPN2DXiMsVn7XUKtOW1CS"},{"number":"3","trackName":"Save Your Tears","artist":"The Weeknd","streams":"147732","url":"https://open.spotify.com/track/5QO79kh1waicV47BqGRL3g"},{"number":"4","trackName":"Blinding Lights","artist":"The Weeknd","streams":"110493","url":"https://open.spotify.com/track/0VjIjW4GlUZAMYd2vXMi3b"},{"number":"5","trackName":"Up","artist":"Cardi B","streams":"107625","url":"https://open.spotify.com/track/1M4OcYkxAtu3ErzSgDEfoi"},{"number":"6","trackName":"WITHOUT YOU","artist":"The Kid LAROI","streams":"105256","url":"https://open.spotify.com/track/27OeeYzk6klgBh83TSvGMA"},{"number":"7","trackName":"Good Days","artist":"SZA","streams":"104951","url":"https://open.spotify.com/track/3YJJjQPAbDT7mGpX3WtQ9A"},{"number":"8","trackName":"Mood (feat. iann dior)","artist":"24kGoldn","streams":"102077","url":"https://open.spotify.com/track/3tjFYV6RSFtuktYl3ZtYcq"},{"number":"9","trackName":"Whoopty","artist":"CJ","streams":"100413","url":"https://open.spotify.com/track/5vGLcdRuSbUhD8ScwsGSdA"},{"number":"10","trackName":"Levitating (feat. DaBaby)","artist":"Dua Lipa","streams":"96744","url":"https://open.spotify.com/track/5nujrmhLynf4yMoMtj8AQF"}],"CH":[{"number":"1","trackName":"drivers license","artist":"Olivia Rodrigo","streams":"35768","url":"https://open.spotify.com/track/7lPN2DXiMsVn7XUKtOW1CS"},{"number":"2","trackName":"Save Your Tears","artist":"The Weeknd","streams":"30898","url":"https://open.spotify.com/track/5QO79kh1waicV47BqGRL3g"},{"number":"3","trackName":"The Business","artist":"Tiësto","streams":"27319","url":"https://open.spotify.com/track/6f3Slt0GbA2bPZlz0aIFXN"},{"number":"4","trackName":"Astronaut In The Ocean","artist":"Masked Wolf","streams":"26231","url":"https://open.spotify.com/track/3VT8hOC5vuDXBsHrR53WFh"},{"number":"5","trackName":"Calling My Phone","artist":"Lil Tjay","streams":"25759","url":"https://open.spotify.com/track/5Kskr9LcNYa0tpt5f0ZEJx"},{"number":"6","trackName":"Whoopty","artist":"CJ","streams":"25497","url":"https://open.spotify.com/track/5vGLcdRuSbUhD8ScwsGSdA"},{"number":"7","trackName":"Blinding Lights","artist":"The Weeknd","streams":"24864","url":"https://open.spotify.com/track/0VjIjW4GlUZAMYd2vXMi3b"},{"number":"8","trackName":"WITHOUT YOU","artist":"The Kid LAROI","streams":"24415","url":"https://open.spotify.com/track/27OeeYzk6klgBh83TSvGMA"},{"number":"9","trackName":"All We Got (feat. KIDDO)","artist":"Robin Schulz","streams":"23182","url":"https://open.spotify.com/track/1FP9s72rDYty6mfoOEYKnE"},{"number":"10","trackName":"Jerusalema (feat. Nomcebo Zikode)","artist":"Master KG","streams":"22328","url":"https://open.spotify.com/track/2MlOUXmcofMackX3bxfSwi"}],"CL":[{"number":"1","trackName":"Bandido","artist":"Myke Towers","streams":"322313","url":"https://open.spotify.com/track/1xK1Gg9SxG8fy2Ya373oqb"},{"number":"2","trackName":"DÁKITI","artist":"Bad Bunny","streams":"283099","url":"https://open.spotify.com/track/4MzXwWMhyBbmu6hOcLVD49"},{"number":"3","trackName":"LA NOCHE DE ANOCHE","artist":"Bad Bunny","streams":"240342","url":"https://open.spotify.com/track/2XIc1pqjXV3Cr2BQUGNBck"},{"number":"4","trackName":"Hecha Pa' Mi","artist":"Boza","streams":"229188","url":"https://open.spotify.com/track/3VvA1wSxukMLsvXoXtlwWx"},{"number":"5","trackName":"BICHOTA","artist":"KAROL G","streams":"219564","url":"https://open.spotify.com/track/7vrJn5hDSXRmdXoR30KgF1"},{"number":"6","trackName":"Fiel","artist":"Los Legendarios","streams":"213010","url":"https://open.spotify.com/track/7Bk0uXKk1uPT0XuQbpFzvs"},{"number":"7","trackName":"Reloj","artist":"Rauw Alejandro","streams":"191457","url":"https://open.spotify.com/track/4loQgPwJHocL3dFwLfjb1J"},{"number":"8","trackName":"Polvo","artist":"Nicky Jam","streams":"177175","url":"https://open.spotify.com/track/68mrW6gXHgupgSiDHgaDi5"},{"number":"9","trackName":"TE MUDASTE","artist":"Bad Bunny","streams":"168515","url":"https://open.spotify.com/track/5RubKOuDoPn5Kj5TLVxSxY"},{"number":"10","trackName":"No Te Enamores - Remix","artist":"Milly","streams":"159783","url":"https://open.spotify.com/track/2mM3gZ0BbPwPPMelbA8vgt"}],"CO":[{"number":"1","trackName":"DÁKITI","artist":"Bad Bunny","streams":"98995","url":"https://open.spotify.com/track/4MzXwWMhyBbmu6hOcLVD49"},{"number":"2","trackName":"Bandido","artist":"Myke Towers","streams":"98463","url":"https://open.spotify.com/track/1xK1Gg9SxG8fy2Ya373oqb"},{"number":"3","trackName":"LA NOCHE DE ANOCHE","artist":"Bad Bunny","streams":"82936","url":"https://open.spotify.com/track/2XIc1pqjXV3Cr2BQUGNBck"},{"number":"4","trackName":"BICHOTA","artist":"KAROL G","streams":"80759","url":"https://open.spotify.com/track/7vrJn5hDSXRmdXoR30KgF1"},{"number":"5","trackName":"Reloj","artist":"Rauw Alejandro","streams":"66830","url":"https://open.spotify.com/track/4loQgPwJHocL3dFwLfjb1J"},{"number":"6","trackName":"Hecha Pa' Mi","artist":"Boza","streams":"66759","url":"https://open.spotify.com/track/3VvA1wSxukMLsvXoXtlwWx"},{"number":"7","trackName":"CHIMBITA","artist":"Feid","streams":"62807","url":"https://open.spotify.com/track/5xwjEzvJ2OSdnHlzusKNYA"},{"number":"8","trackName":"La Nota","artist":"Manuel Turizo","streams":"62176","url":"https://open.spotify.com/track/7ndTONDDRFGiPnnhOzOXxq"},{"number":"9","trackName":"Hawái","artist":"Maluma","streams":"60964","url":"https://open.spotify.com/track/1yoMvmasuxZfqHEipJhRbp"},{"number":"10","trackName":"LOCATION","artist":"KAROL G","streams":"55278","url":"https://open.spotify.com/track/5Km4r87BoX2qqtoprYS1gh"}],"CR":[{"number":"1","trackName":"Bandido","artist":"Myke Towers","streams":"33430","url":"https://open.spotify.com/track/1xK1Gg9SxG8fy2Ya373oqb"},{"number":"2","trackName":"DÁKITI","artist":"Bad Bunny","streams":"31151","url":"https://open.spotify.com/track/4MzXwWMhyBbmu6hOcLVD49"},{"number":"3","trackName":"LA NOCHE DE ANOCHE","artist":"Bad Bunny","streams":"25260","url":"https://open.spotify.com/track/2XIc1pqjXV3Cr2BQUGNBck"},{"number":"4","trackName":"BICHOTA","artist":"KAROL G","streams":"24677","url":"https://open.spotify.com/track/7vrJn5hDSXRmdXoR30KgF1"},{"number":"5","trackName":"Hecha Pa' Mi","artist":"Boza","streams":"24128","url":"https://open.spotify.com/track/3VvA1wSxukMLsvXoXtlwWx"},{"number":"6","trackName":"Reloj","artist":"Rauw Alejandro","streams":"19122","url":"https://open.spotify.com/track/4loQgPwJHocL3dFwLfjb1J"},{"number":"7","trackName":"Chica Ideal","artist":"Sebastian Yatra","streams":"17844","url":"https://open.spotify.com/track/21N4Buj4xsyLb218lYle61"},{"number":"8","trackName":"Hawái","artist":"Maluma","streams":"17723","url":"https://open.spotify.com/track/1yoMvmasuxZfqHEipJhRbp"},{"number":"9","trackName":"La Tóxica","artist":"Farruko","streams":"16579","url":"https://open.spotify.com/track/15OjBeqNX3bShsGYQbteRv"},{"number":"10","trackName":"La Nota","artist":"Manuel Turizo","streams":"16556","url":"https://open.spotify.com/track/7ndTONDDRFGiPnnhOzOXxq"}],"CZ":[{"number":"1","trackName":"Rodinnej Typ","artist":"Yzomandias","streams":"28523","url":"https://open.spotify.com/track/35nvMkQglkoeydD81a0b77"},{"number":"2","trackName":"BodyBag","artist":"Yzomandias","streams":"24546","url":"https://open.spotify.com/track/3fBpzO81OXrmZPKL0KG8LF"},{"number":"3","trackName":"Astronaut In The Ocean","artist":"Masked Wolf","streams":"23273","url":"https://open.spotify.com/track/3VT8hOC5vuDXBsHrR53WFh"},{"number":"4","trackName":"drivers license","artist":"Olivia Rodrigo","streams":"18434","url":"https://open.spotify.com/track/7lPN2DXiMsVn7XUKtOW1CS"},{"number":"5","trackName":"The Business","artist":"Tiësto","streams":"18083","url":"https://open.spotify.com/track/6f3Slt0GbA2bPZlz0aIFXN"},{"number":"6","trackName":"JTNJD All-Star MegaRemix","artist":"Yzomandias","streams":"17276","url":"https://open.spotify.com/track/0Z5RW9k0pxlbsVx2eyOFI2"},{"number":"7","trackName":"Rauš","artist":"Yzomandias","streams":"15785","url":"https://open.spotify.com/track/0u2mfizmigNtOtYQuTJIKm"},{"number":"8","trackName":"Mood (feat. iann dior)","artist":"24kGoldn","streams":"15738","url":"https://open.spotify.com/track/3tjFYV6RSFtuktYl3ZtYcq"},{"number":"9","trackName":"Blinding Lights","artist":"The Weeknd","streams":"15515","url":"https://open.spotify.com/track/0VjIjW4GlUZAMYd2vXMi3b"},{"number":"10","trackName":"Save Your Tears","artist":"The Weeknd","streams":"14977","url":"https://open.spotify.com/track/5QO79kh1waicV47BqGRL3g"}],"DE":[{"number":"1","trackName":"Ohne Dich","artist":"KASIMIR1441","streams":"494856","url":"https://open.spotify.com/track/4hSJUp6k7QeHLxU32MrLIU"},{"number":"2","trackName":"No Comprendo","artist":"Jamule","streams":"328419","url":"https://open.spotify.com/track/5ezbc8nalmV7JqLQQfHwTV"},{"number":"3","trackName":"drivers license","artist":"Olivia Rodrigo","streams":"314469","url":"https://open.spotify.com/track/7lPN2DXiMsVn7XUKtOW1CS"},{"number":"4","trackName":"Astronaut In The Ocean","artist":"Masked Wolf","streams":"312614","url":"https://open.spotify.com/track/3VT8hOC5vuDXBsHrR53WFh"},{"number":"5","trackName":"The Business","artist":"Tiësto","streams":"292154","url":"https://open.spotify.com/track/6f3Slt0GbA2bPZlz0aIFXN"},{"number":"6","trackName":"Save Your Tears","artist":"The Weeknd","streams":"255601","url":"https://open.spotify.com/track/5QO79kh1waicV47BqGRL3g"},{"number":"7","trackName":"Your Love (9PM)","artist":"ATB","streams":"242779","url":"https://open.spotify.com/track/5YaskwnGDZFDRipaqzbwQx"},{"number":"8","trackName":"WITHOUT YOU","artist":"The Kid LAROI","streams":"241283","url":"https://open.spotify.com/track/27OeeYzk6klgBh83TSvGMA"},{"number":"9","trackName":"Wenn sie ruft","artist":"Miksu / Macloud","streams":"234406","url":"https://open.spotify.com/track/0O214XAfoQz8VVH83xpAjz"},{"number":"10","trackName":"Angst","artist":"Apache 207","streams":"211213","url":"https://open.spotify.com/track/5yUzqd3H7cmJ1no6B4uTzu"}],"DK":[{"number":"1","trackName":"MCQUEEN","artist":"RH","streams":"59505","url":"https://open.spotify.com/track/29s2dhQ00vpr6eTI00Kc77"},{"number":"2","trackName":"drivers license","artist":"Olivia Rodrigo","streams":"57612","url":"https://open.spotify.com/track/7lPN2DXiMsVn7XUKtOW1CS"},{"number":"3","trackName":"No Evil","artist":"Branco","streams":"55306","url":"https://open.spotify.com/track/7GT52p7q3ZeE97R6L8w5lU"},{"number":"4","trackName":"Save Your Tears","artist":"The Weeknd","streams":"53620","url":"https://open.spotify.com/track/5QO79kh1waicV47BqGRL3g"},{"number":"5","trackName":"WITHOUT YOU","artist":"The Kid LAROI","streams":"49811","url":"https://open.spotify.com/track/27OeeYzk6klgBh83TSvGMA"},{"number":"6","trackName":"Calling My Phone","artist":"Lil Tjay","streams":"46576","url":"https://open.spotify.com/track/5Kskr9LcNYa0tpt5f0ZEJx"},{"number":"7","trackName":"The Business","artist":"Tiësto","streams":"41359","url":"https://open.spotify.com/track/6f3Slt0GbA2bPZlz0aIFXN"},{"number":"8","trackName":"Kærlighedssangen","artist":"Jimilian","streams":"37477","url":"https://open.spotify.com/track/6WELXrF1hsdUZEcasR1DGG"},{"number":"9","trackName":"Bando Bitch","artist":"Branco","streams":"35970","url":"https://open.spotify.com/track/46EJP4xRtHEzOthuhDqo54"},{"number":"10","trackName":"Blinding Lights","artist":"The Weeknd","streams":"34537","url":"https://open.spotify.com/track/0VjIjW4GlUZAMYd2vXMi3b"}],"DO":[{"number":"1","trackName":"DÁKITI","artist":"Bad Bunny","streams":"20689","url":"https://open.spotify.com/track/4MzXwWMhyBbmu6hOcLVD49"},{"number":"2","trackName":"Bandido","artist":"Myke Towers","streams":"20398","url":"https://open.spotify.com/track/1xK1Gg9SxG8fy2Ya373oqb"},{"number":"3","trackName":"LA NOCHE DE ANOCHE","artist":"Bad Bunny","streams":"19143","url":"https://open.spotify.com/track/2XIc1pqjXV3Cr2BQUGNBck"},{"number":"4","trackName":"Ella No Es Tuya - Remix","artist":"Rochy RD","streams":"13435","url":"https://open.spotify.com/track/5YYW3yRktprLRr47WK219Y"},{"number":"5","trackName":"Reloj","artist":"Rauw Alejandro","streams":"12217","url":"https://open.spotify.com/track/4loQgPwJHocL3dFwLfjb1J"},{"number":"6","trackName":"BICHOTA","artist":"KAROL G","streams":"12198","url":"https://open.spotify.com/track/7vrJn5hDSXRmdXoR30KgF1"},{"number":"7","trackName":"BOOKER T","artist":"Bad Bunny","streams":"11899","url":"https://open.spotify.com/track/26w9NTiE9NGjW1ZvIOd1So"},{"number":"8","trackName":"Hecha Pa' Mi","artist":"Boza","streams":"11260","url":"https://open.spotify.com/track/3VvA1wSxukMLsvXoXtlwWx"},{"number":"9","trackName":"La Nota","artist":"Manuel Turizo","streams":"10524","url":"https://open.spotify.com/track/7ndTONDDRFGiPnnhOzOXxq"},{"number":"10","trackName":"TE MUDASTE","artist":"Bad Bunny","streams":"9719","url":"https://open.spotify.com/track/5RubKOuDoPn5Kj5TLVxSxY"}],"EC":[{"number":"1","trackName":"DÁKITI","artist":"Bad Bunny","streams":"50600","url":"https://open.spotify.com/track/4MzXwWMhyBbmu6hOcLVD49"},{"number":"2","trackName":"Bandido","artist":"Myke Towers","streams":"44696","url":"https://open.spotify.com/track/1xK1Gg9SxG8fy2Ya373oqb"},{"number":"3","trackName":"BICHOTA","artist":"KAROL G","streams":"40986","url":"https://open.spotify.com/track/7vrJn5hDSXRmdXoR30KgF1"},{"number":"4","trackName":"LA NOCHE DE ANOCHE","artist":"Bad Bunny","streams":"40444","url":"https://open.spotify.com/track/2XIc1pqjXV3Cr2BQUGNBck"},{"number":"5","trackName":"Hecha Pa' Mi","artist":"Boza","streams":"33088","url":"https://open.spotify.com/track/3VvA1wSxukMLsvXoXtlwWx"},{"number":"6","trackName":"Reloj","artist":"Rauw Alejandro","streams":"28185","url":"https://open.spotify.com/track/4loQgPwJHocL3dFwLfjb1J"},{"number":"7","trackName":"Chica Ideal","artist":"Sebastian Yatra","streams":"26616","url":"https://open.spotify.com/track/21N4Buj4xsyLb218lYle61"},{"number":"8","trackName":"TE MUDASTE","artist":"Bad Bunny","streams":"26559","url":"https://open.spotify.com/track/5RubKOuDoPn5Kj5TLVxSxY"},{"number":"9","trackName":"Ropa Cara","artist":"Camilo","streams":"25841","url":"https://open.spotify.com/track/7BIy3EGQhg98CsRdKYHnJC"},{"number":"10","trackName":"Hawái","artist":"Maluma","streams":"25574","url":"https://open.spotify.com/track/1yoMvmasuxZfqHEipJhRbp"}],"EE":[{"number":"1","trackName":"drivers license","artist":"Olivia Rodrigo","streams":"4252","url":"https://open.spotify.com/track/7lPN2DXiMsVn7XUKtOW1CS"},{"number":"2","trackName":"Save Your Tears","artist":"The Weeknd","streams":"3352","url":"https://open.spotify.com/track/5QO79kh1waicV47BqGRL3g"},{"number":"3","trackName":"Universum","artist":"Nublu","streams":"3173","url":"https://open.spotify.com/track/7IoTZnck9r11NCj5M0QG81"},{"number":"4","trackName":"Streets","artist":"Doja Cat","streams":"2957","url":"https://open.spotify.com/track/60ynsPSSKe6O3sfwRnIBRf"},{"number":"5","trackName":"WITHOUT YOU","artist":"The Kid LAROI","streams":"2563","url":"https://open.spotify.com/track/27OeeYzk6klgBh83TSvGMA"},{"number":"6","trackName":"Моя голова винтом","artist":"kostromin","streams":"2520","url":"https://open.spotify.com/track/4KrhaZm4JRkNO4HRdLvJIG"},{"number":"7","trackName":"Paraadna","artist":"Nublu","streams":"2480","url":"https://open.spotify.com/track/5VEZQNZWsZaKb1Y2jB8SWJ"},{"number":"8","trackName":"The Business","artist":"Tiësto","streams":"2390","url":"https://open.spotify.com/track/6f3Slt0GbA2bPZlz0aIFXN"},{"number":"9","trackName":"Blinding Lights","artist":"The Weeknd","streams":"2363","url":"https://open.spotify.com/track/0VjIjW4GlUZAMYd2vXMi3b"},{"number":"10","trackName":"Calling My Phone","artist":"Lil Tjay","streams":"2335","url":"https://open.spotify.com/track/5Kskr9LcNYa0tpt5f0ZEJx"}],"ES":[{"number":"1","trackName":"Ella No Es Tuya - Remix","artist":"Rochy RD","streams":"489225","url":"https://open.spotify.com/track/5YYW3yRktprLRr47WK219Y"},{"number":"2","trackName":"Bandido","artist":"Myke Towers","streams":"390835","url":"https://open.spotify.com/track/1xK1Gg9SxG8fy2Ya373oqb"},{"number":"3","trackName":"No Te Enamores - Remix","artist":"Milly","streams":"310811","url":"https://open.spotify.com/track/2mM3gZ0BbPwPPMelbA8vgt"},{"number":"4","trackName":"DÁKITI","artist":"Bad Bunny","streams":"308275","url":"https://open.spotify.com/track/4MzXwWMhyBbmu6hOcLVD49"},{"number":"5","trackName":"Hecha Pa' Mi","artist":"Boza","streams":"262534","url":"https://open.spotify.com/track/3VvA1wSxukMLsvXoXtlwWx"},{"number":"6","trackName":"LA NOCHE DE ANOCHE","artist":"Bad Bunny","streams":"255250","url":"https://open.spotify.com/track/2XIc1pqjXV3Cr2BQUGNBck"},{"number":"7","trackName":"Antes","artist":"Anuel AA","streams":"249822","url":"https://open.spotify.com/track/73O30uMI7n6DuzBmbtO7kC"},{"number":"8","trackName":"Baila Conmigo (with Rauw Alejandro)","artist":"Selena Gomez","streams":"243196","url":"https://open.spotify.com/track/0D75ciM842cdUMKSMfAR9y"},{"number":"9","trackName":"Tú Me Dejaste De Querer","artist":"C. Tangana","streams":"227707","url":"https://open.spotify.com/track/0XinBYhf1X3kdvKQHOX971"},{"number":"10","trackName":"Vete Pal Carajo","artist":"Yan Block","streams":"207003","url":"https://open.spotify.com/track/1mrQYY0NATPCe7WOYcCKf1"}],"FI":[{"number":"1","trackName":"Me ei mennä rikki","artist":"Gasellit","streams":"48447","url":"https://open.spotify.com/track/3KlKNC9vfmdREv97mK0Xce"},{"number":"2","trackName":"drivers license","artist":"Olivia Rodrigo","streams":"39832","url":"https://open.spotify.com/track/7lPN2DXiMsVn7XUKtOW1CS"},{"number":"3","trackName":"I Love You","artist":"Teflon Brothers","streams":"36558","url":"https://open.spotify.com/track/4sFDPk9PwpHWDcXN8rY2oA"},{"number":"4","trackName":"Zen","artist":"Gasellit","streams":"36488","url":"https://open.spotify.com/track/6LRMjIvyLYlC0hcOCbGvlP"},{"number":"5","trackName":"Save Your Tears","artist":"The Weeknd","streams":"35536","url":"https://open.spotify.com/track/5QO79kh1waicV47BqGRL3g"},{"number":"6","trackName":"Astronaut In The Ocean","artist":"Masked Wolf","streams":"33664","url":"https://open.spotify.com/track/3VT8hOC5vuDXBsHrR53WFh"},{"number":"7","trackName":"Tilanne pääl","artist":"Gasellit","streams":"32435","url":"https://open.spotify.com/track/3IcObWyN8xrzVCkJGX4o0N"},{"number":"8","trackName":"WITHOUT YOU","artist":"The Kid LAROI","streams":"30286","url":"https://open.spotify.com/track/27OeeYzk6klgBh83TSvGMA"},{"number":"9","trackName":"Kelle mä soitan","artist":"Ilta","streams":"28058","url":"https://open.spotify.com/track/0JaJLSes2LpFGit36B7tzm"},{"number":"10","trackName":"Lääke","artist":"VIIVI","streams":"27959","url":"https://open.spotify.com/track/5xL99WCxOwOee326Ezf0eP"}],"FR":[{"number":"1","trackName":"Marché noir","artist":"SCH","streams":"190827","url":"https://open.spotify.com/track/4uOiz6kmw0NkJLWAS0etWx"},{"number":"2","trackName":"Fever","artist":"Dua Lipa","streams":"183506","url":"https://open.spotify.com/track/3F1P0QzdXtBz0MXy7KIO5w"},{"number":"3","trackName":"Cœur noir","artist":"Eva","streams":"173566","url":"https://open.spotify.com/track/2SYYB9pwxbYJducVc2xGWD"},{"number":"4","trackName":"GIRL LIKE ME","artist":"Black Eyed Peas","streams":"168825","url":"https://open.spotify.com/track/2vBET2pmrQqafaS6zIaYta"},{"number":"5","trackName":"DÁKITI","artist":"Bad Bunny","streams":"164408","url":"https://open.spotify.com/track/4MzXwWMhyBbmu6hOcLVD49"},{"number":"6","trackName":"Tout en Gucci","artist":"Ninho","streams":"155706","url":"https://open.spotify.com/track/0i5GJckWb9uCZU4jcGoBca"},{"number":"7","trackName":"Bande organisée","artist":"13 Organisé","streams":"154259","url":"https://open.spotify.com/track/717QGTmZdkemDaCo1vQHG0"},{"number":"8","trackName":"RATPI WORLD","artist":"Booba","streams":"153497","url":"https://open.spotify.com/track/2ZjTAieewsBC24kPGfLagc"},{"number":"9","trackName":"Mother Fuck","artist":"Jul","streams":"137827","url":"https://open.spotify.com/track/6atYbfU3m7CYTDe4LzQlUI"},{"number":"10","trackName":"Cosmos - feat. PLK","artist":"Rim'K","streams":"133571","url":"https://open.spotify.com/track/5hM1Bta5Ej1rRyOXStRIzH"}],"GR":[{"number":"1","trackName":"Voodoo","artist":"Light","streams":"22843","url":"https://open.spotify.com/track/6tGl1mj5CyoB1hUtOKyhkQ"},{"number":"2","trackName":"Prince","artist":"Fy","streams":"22699","url":"https://open.spotify.com/track/4M8I7zcnQYsGH5thn1J0sC"},{"number":"3","trackName":"Gymni","artist":"Light","streams":"15548","url":"https://open.spotify.com/track/0Vo6x7xCIqQlnm2XbLZ6mF"},{"number":"4","trackName":"XILIOMETRA","artist":"Mad Clip","streams":"13597","url":"https://open.spotify.com/track/0Az2D1ByNU09je0ZtzDcHm"},{"number":"5","trackName":"Geitonia","artist":"MG","streams":"12338","url":"https://open.spotify.com/track/4euI2v1IEEIUKdFs5WJmzQ"},{"number":"6","trackName":"Calling My Phone","artist":"Lil Tjay","streams":"12298","url":"https://open.spotify.com/track/5Kskr9LcNYa0tpt5f0ZEJx"},{"number":"7","trackName":"Whoopty","artist":"CJ","streams":"12290","url":"https://open.spotify.com/track/5vGLcdRuSbUhD8ScwsGSdA"},{"number":"8","trackName":"Joker","artist":"Lamanif","streams":"11824","url":"https://open.spotify.com/track/11nUDQBQQZw37Osi7qWBDL"},{"number":"9","trackName":"Street Values","artist":"VLOSPA","streams":"11617","url":"https://open.spotify.com/track/5008Rz0J8beglZBqnvSUCn"},{"number":"10","trackName":"Ring","artist":"Fy","streams":"11134","url":"https://open.spotify.com/track/5g5GOBG3mTODUxegwjK4VL"}],"GT":[{"number":"1","trackName":"DÁKITI","artist":"Bad Bunny","streams":"43834","url":"https://open.spotify.com/track/4MzXwWMhyBbmu6hOcLVD49"},{"number":"2","trackName":"Bandido","artist":"Myke Towers","streams":"39441","url":"https://open.spotify.com/track/1xK1Gg9SxG8fy2Ya373oqb"},{"number":"3","trackName":"LA NOCHE DE ANOCHE","artist":"Bad Bunny","streams":"37253","url":"https://open.spotify.com/track/2XIc1pqjXV3Cr2BQUGNBck"},{"number":"4","trackName":"BICHOTA","artist":"KAROL G","streams":"34262","url":"https://open.spotify.com/track/7vrJn5hDSXRmdXoR30KgF1"},{"number":"5","trackName":"Reloj","artist":"Rauw Alejandro","streams":"28841","url":"https://open.spotify.com/track/4loQgPwJHocL3dFwLfjb1J"},{"number":"6","trackName":"Hecha Pa' Mi","artist":"Boza","streams":"26883","url":"https://open.spotify.com/track/3VvA1wSxukMLsvXoXtlwWx"},{"number":"7","trackName":"Hawái","artist":"Maluma","streams":"24044","url":"https://open.spotify.com/track/1yoMvmasuxZfqHEipJhRbp"},{"number":"8","trackName":"La Tóxica","artist":"Farruko","streams":"23355","url":"https://open.spotify.com/track/15OjBeqNX3bShsGYQbteRv"},{"number":"9","trackName":"TE MUDASTE","artist":"Bad Bunny","streams":"22276","url":"https://open.spotify.com/track/5RubKOuDoPn5Kj5TLVxSxY"},{"number":"10","trackName":"Chica Ideal","artist":"Sebastian Yatra","streams":"21413","url":"https://open.spotify.com/track/21N4Buj4xsyLb218lYle61"}],"HK":[{"number":"1","trackName":"一人之境 in C major","artist":"Terence Lam","streams":"19564","url":"https://open.spotify.com/track/32QnXosZq7A11knnBAEqk7"},{"number":"2","trackName":"時光倒流一句話","artist":"Terence Lam","streams":"16913","url":"https://open.spotify.com/track/63QmxPL3QlchvXcHLsI6UM"},{"number":"3","trackName":"隔離 - Studio Live Duet","artist":"Jace Chan","streams":"15733","url":"https://open.spotify.com/track/4xL01OuFjqizPDclF8gDpl"},{"number":"4","trackName":"drivers license","artist":"Olivia Rodrigo","streams":"14384","url":"https://open.spotify.com/track/7lPN2DXiMsVn7XUKtOW1CS"},{"number":"5","trackName":"E先生 連環不幸事件","artist":"Edan 呂爵安","streams":"14232","url":"https://open.spotify.com/track/06sDxr7MbbwFyTP1f6rvvl"},{"number":"6","trackName":"下一位前度","artist":"Terence Lam","streams":"14225","url":"https://open.spotify.com/track/0Q3jOuEpx8Esi2qZMQSghl"},{"number":"7","trackName":"是但求其愛","artist":"Eason Chan","streams":"13696","url":"https://open.spotify.com/track/4IkQXb1IdIziAJmO3FODo7"},{"number":"8","trackName":"刻在我心底的名字 (Your Name Engraved Herein) - 電影<刻在你心底的名字>主題曲","artist":"Crowd Lu","streams":"13270","url":"https://open.spotify.com/track/3OC84eKMxRJ4x0Hcwl9i4i"},{"number":"9","trackName":"銀河修理員","artist":"Dear Jane","streams":"12774","url":"https://open.spotify.com/track/0pupuSkMBGpzsqG3fWcyPe"},{"number":"10","trackName":"俏郎君","artist":"Hins Cheung","streams":"11853","url":"https://open.spotify.com/track/4ckh5VN2HYQ8TzS51Nh7ol"}],"HN":[{"number":"1","trackName":"DÁKITI","artist":"Bad Bunny","streams":"16186","url":"https://open.spotify.com/track/4MzXwWMhyBbmu6hOcLVD49"},{"number":"2","trackName":"LA NOCHE DE ANOCHE","artist":"Bad Bunny","streams":"13822","url":"https://open.spotify.com/track/2XIc1pqjXV3Cr2BQUGNBck"},{"number":"3","trackName":"Bandido","artist":"Myke Towers","streams":"13763","url":"https://open.spotify.com/track/1xK1Gg9SxG8fy2Ya373oqb"},{"number":"4","trackName":"BICHOTA","artist":"KAROL G","streams":"10799","url":"https://open.spotify.com/track/7vrJn5hDSXRmdXoR30KgF1"},{"number":"5","trackName":"TE MUDASTE","artist":"Bad Bunny","streams":"9484","url":"https://open.spotify.com/track/5RubKOuDoPn5Kj5TLVxSxY"},{"number":"6","trackName":"Reloj","artist":"Rauw Alejandro","streams":"9249","url":"https://open.spotify.com/track/4loQgPwJHocL3dFwLfjb1J"},{"number":"7","trackName":"Hecha Pa' Mi","artist":"Boza","streams":"8640","url":"https://open.spotify.com/track/3VvA1wSxukMLsvXoXtlwWx"},{"number":"8","trackName":"BOOKER T","artist":"Bad Bunny","streams":"8171","url":"https://open.spotify.com/track/26w9NTiE9NGjW1ZvIOd1So"},{"number":"9","trackName":"Hawái","artist":"Maluma","streams":"7458","url":"https://open.spotify.com/track/1yoMvmasuxZfqHEipJhRbp"},{"number":"10","trackName":"La Tóxica","artist":"Farruko","streams":"7438","url":"https://open.spotify.com/track/15OjBeqNX3bShsGYQbteRv"}],"HU":[{"number":"1","trackName":"The Business","artist":"Tiësto","streams":"18633","url":"https://open.spotify.com/track/6f3Slt0GbA2bPZlz0aIFXN"},{"number":"2","trackName":"drivers license","artist":"Olivia Rodrigo","streams":"14831","url":"https://open.spotify.com/track/7lPN2DXiMsVn7XUKtOW1CS"},{"number":"3","trackName":"Üres szívek","artist":"Nemazalány","streams":"13863","url":"https://open.spotify.com/track/78Jj0xPR2y4KMAtYuWpRly"},{"number":"4","trackName":"Save Your Tears","artist":"The Weeknd","streams":"13613","url":"https://open.spotify.com/track/5QO79kh1waicV47BqGRL3g"},{"number":"5","trackName":"Head & Heart (feat. MNEK)","artist":"Joel Corry","streams":"13094","url":"https://open.spotify.com/track/6cx06DFPPHchuUAcTxznu9"},{"number":"6","trackName":"Paradise (feat. Dermot Kennedy)","artist":"MEDUZA","streams":"12827","url":"https://open.spotify.com/track/6ft4hAq6yde8jPZY2i5zLr"},{"number":"7","trackName":"Astronaut In The Ocean","artist":"Masked Wolf","streams":"12460","url":"https://open.spotify.com/track/3VT8hOC5vuDXBsHrR53WFh"},{"number":"8","trackName":"Blinding Lights","artist":"The Weeknd","streams":"12381","url":"https://open.spotify.com/track/0VjIjW4GlUZAMYd2vXMi3b"},{"number":"9","trackName":"Mood (feat. iann dior)","artist":"24kGoldn","streams":"12158","url":"https://open.spotify.com/track/3tjFYV6RSFtuktYl3ZtYcq"},{"number":"10","trackName":"Head Shoulders Knees & Toes (feat. Norma Jean Martine)","artist":"Ofenbach","streams":"12127","url":"https://open.spotify.com/track/6i7zAdNhzUN2k1HcrBxPHG"}],"ID":[{"number":"1","trackName":"Bertaut","artist":"Nadin Amizah","streams":"279741","url":"https://open.spotify.com/track/630DpnzdfjdVqv2yLfPbAX"},{"number":"2","trackName":"Blue Jeans","artist":"GANGGA","streams":"259178","url":"https://open.spotify.com/track/4kfjA6WfgKBt7I7YKuDCkU"},{"number":"3","trackName":"At My Worst","artist":"Pink Sweat$","streams":"244695","url":"https://open.spotify.com/track/2MJz8BxxMsERULatmBikDH"},{"number":"4","trackName":"drivers license","artist":"Olivia Rodrigo","streams":"222863","url":"https://open.spotify.com/track/7lPN2DXiMsVn7XUKtOW1CS"},{"number":"5","trackName":"Melukis Senja","artist":"Budi Doremi","streams":"210810","url":"https://open.spotify.com/track/0ZEYRVISCaqz5yamWZWzaA"},{"number":"6","trackName":"Mungkin Hari Ini Esok Atau Nanti","artist":"Anneth","streams":"203430","url":"https://open.spotify.com/track/7n5nvulc1oW1ErpeTrNezI"},{"number":"7","trackName":"Snowman","artist":"Sia","streams":"168988","url":"https://open.spotify.com/track/7uoFMmxln0GPXQ0AcCBXRq"},{"number":"8","trackName":"HEARTBREAK ANNIVERSARY","artist":"Giveon","streams":"161030","url":"https://open.spotify.com/track/3FAJ6O0NOHQV8Mc5Ri6ENp"},{"number":"9","trackName":"Weak","artist":"Larissa Lambert","streams":"155457","url":"https://open.spotify.com/track/07MW63ok3ptSKwaTWEN0o8"},{"number":"10","trackName":"I Just Couldn't Save You Tonight (feat. Aurélie) - Story of Kale - Original Motion Picture Soundtrack","artist":"Ardhito Pramono","streams":"152442","url":"https://open.spotify.com/track/5AkV53fo1u01mi8r22JNeF"}],"IE":[{"number":"1","trackName":"drivers license","artist":"Olivia Rodrigo","streams":"65489","url":"https://open.spotify.com/track/7lPN2DXiMsVn7XUKtOW1CS"},{"number":"2","trackName":"The Business","artist":"Tiësto","streams":"42502","url":"https://open.spotify.com/track/6f3Slt0GbA2bPZlz0aIFXN"},{"number":"3","trackName":"Calling My Phone","artist":"Lil Tjay","streams":"41219","url":"https://open.spotify.com/track/5Kskr9LcNYa0tpt5f0ZEJx"},{"number":"4","trackName":"Paradise (feat. Dermot Kennedy)","artist":"MEDUZA","streams":"38665","url":"https://open.spotify.com/track/6ft4hAq6yde8jPZY2i5zLr"},{"number":"5","trackName":"WITHOUT YOU","artist":"The Kid LAROI","streams":"37800","url":"https://open.spotify.com/track/27OeeYzk6klgBh83TSvGMA"},{"number":"6","trackName":"Save Your Tears","artist":"The Weeknd","streams":"34239","url":"https://open.spotify.com/track/5QO79kh1waicV47BqGRL3g"},{"number":"7","trackName":"Giants","artist":"Dermot Kennedy","streams":"27962","url":"https://open.spotify.com/track/43CHdbHYdcbUWP10UFKyZ7"},{"number":"8","trackName":"Don't Play","artist":"Anne-Marie","streams":"26528","url":"https://open.spotify.com/track/4I5bvu2KDsrCg0EWHIcvul"},{"number":"9","trackName":"Get Out My Head","artist":"Shane Codd","streams":"26517","url":"https://open.spotify.com/track/055Mme9ReKK99jRFA5UJ55"},{"number":"10","trackName":"Head & Heart (feat. MNEK)","artist":"Joel Corry","streams":"25912","url":"https://open.spotify.com/track/6cx06DFPPHchuUAcTxznu9"}],"IL":[{"number":"1","trackName":"רוצה שלום","artist":"Raviv Kaner","streams":"19379","url":"https://open.spotify.com/track/4L4dPjtEVEpZ0ER2deHAJA"},{"number":"2","trackName":"שקיעות אדומות","artist":"Eden Hason","streams":"17637","url":"https://open.spotify.com/track/74pfNNxGlwSyokwtqxHcDa"},{"number":"3","trackName":"באור גדול","artist":"Eyal Golan","streams":"17208","url":"https://open.spotify.com/track/3ygLMqx3CNVJmQAnriDDh2"},{"number":"4","trackName":"רסיסים","artist":"Raviv Kaner","streams":"16600","url":"https://open.spotify.com/track/4qAHhdpiGcbzqwjqmwuXwj"},{"number":"5","trackName":"Save Your Tears","artist":"The Weeknd","streams":"15296","url":"https://open.spotify.com/track/5QO79kh1waicV47BqGRL3g"},{"number":"6","trackName":"Blinding Lights","artist":"The Weeknd","streams":"14787","url":"https://open.spotify.com/track/0VjIjW4GlUZAMYd2vXMi3b"},{"number":"7","trackName":"drivers license","artist":"Olivia Rodrigo","streams":"14766","url":"https://open.spotify.com/track/7lPN2DXiMsVn7XUKtOW1CS"},{"number":"8","trackName":"שלמים","artist":"Idan Rafael Haviv","streams":"12937","url":"https://open.spotify.com/track/72W6xVQGdKHQl348KYgwg2"},{"number":"9","trackName":"שרק תחייך","artist":"Yuval Dayan","streams":"12692","url":"https://open.spotify.com/track/7vn9SIc4NraLuIMzUeCK2o"},{"number":"10","trackName":"פסקול חיי","artist":"Omer Adam","streams":"12509","url":"https://open.spotify.com/track/1oX73Qk8YvqqzrYMRyLH0b"}],"IN":[{"number":"1","trackName":"Brown Munde","artist":"AP Dhillon","streams":"366111","url":"https://open.spotify.com/track/58f4twRnbZOOVUhMUpplJ4"},{"number":"2","trackName":"Ghalat Fehmi - From \"Superstar\"","artist":"Asim Azhar","streams":"241292","url":"https://open.spotify.com/track/5mnvugwfFYnJm9zuyGkgqF"},{"number":"3","trackName":"Libaas","artist":"Kaka","streams":"169477","url":"https://open.spotify.com/track/0vqw3BCyNr3DDVBmjD21H8"},{"number":"4","trackName":"Shayad","artist":"Pritam","streams":"165151","url":"https://open.spotify.com/track/1smFN2CLqGROu0J0UyvDfL"},{"number":"5","trackName":"drivers license","artist":"Olivia Rodrigo","streams":"160085","url":"https://open.spotify.com/track/7lPN2DXiMsVn7XUKtOW1CS"},{"number":"6","trackName":"Agar Tum Saath Ho (From \"Tamasha\")","artist":"Alka Yagnik","streams":"147638","url":"https://open.spotify.com/track/2FCXQHugkoHE1K3tiDu8pu"},{"number":"7","trackName":"Guilty","artist":"Inder Chahal","streams":"146755","url":"https://open.spotify.com/track/2W9awzkFJzPRddvLXtCSOU"},{"number":"8","trackName":"Saiyaan Ji","artist":"Yo Yo Honey Singh","streams":"144759","url":"https://open.spotify.com/track/39QJ7KkN3L8LLqQqsO85W1"},{"number":"9","trackName":"Astronaut In The Ocean","artist":"Masked Wolf","streams":"140420","url":"https://open.spotify.com/track/3VT8hOC5vuDXBsHrR53WFh"},{"number":"10","trackName":"Blinding Lights","artist":"The Weeknd","streams":"126365","url":"https://open.spotify.com/track/0VjIjW4GlUZAMYd2vXMi3b"}],"IS":[{"number":"1","trackName":"Calling My Phone","artist":"Lil Tjay","streams":"7105","url":"https://open.spotify.com/track/5Kskr9LcNYa0tpt5f0ZEJx"},{"number":"2","trackName":"Save Your Tears","artist":"The Weeknd","streams":"6041","url":"https://open.spotify.com/track/5QO79kh1waicV47BqGRL3g"},{"number":"3","trackName":"Ef ástin er hrein (feat. GDRN)","artist":"Jón Jónsson","streams":"5800","url":"https://open.spotify.com/track/5wGoaKvq8Vlst7ZqKyQbvn"},{"number":"4","trackName":"drivers license","artist":"Olivia Rodrigo","streams":"5688","url":"https://open.spotify.com/track/7lPN2DXiMsVn7XUKtOW1CS"},{"number":"5","trackName":"Spurningar (feat. Páll Óskar)","artist":"Birnir","streams":"5636","url":"https://open.spotify.com/track/5VrbuzqAjCAFSa7MpGRXWI"},{"number":"6","trackName":"Rólegur Kúreki","artist":"BRÍET","streams":"5224","url":"https://open.spotify.com/track/5qI0p2E7BxBxYRJknYr6Gg"},{"number":"7","trackName":"Segðu mér","artist":"Friðrik Dór","streams":"4840","url":"https://open.spotify.com/track/04ZMCgKlsRcTDrxGMKCrAx"},{"number":"8","trackName":"Good Days","artist":"SZA","streams":"3388","url":"https://open.spotify.com/track/3YJJjQPAbDT7mGpX3WtQ9A"},{"number":"9","trackName":"Esjan","artist":"BRÍET","streams":"3330","url":"https://open.spotify.com/track/7DRDJ5ZzU7mj7CfRxGYzOY"},{"number":"10","trackName":"The Business","artist":"Tiësto","streams":"3165","url":"https://open.spotify.com/track/6f3Slt0GbA2bPZlz0aIFXN"}],"IT":[{"number":"1","trackName":"LA CANZONE NOSTRA ⟁ ︎(con BLANCO & SALMO)","artist":"MACE","streams":"418223","url":"https://open.spotify.com/track/1uXJYnCsXy2v50y0fDEEiV"},{"number":"2","trackName":"lady","artist":"sangiovanni","streams":"207195","url":"https://open.spotify.com/track/2uyQXAGGwHuQVsu04OTVsB"},{"number":"3","trackName":"Destri","artist":"Gazzelle","streams":"199742","url":"https://open.spotify.com/track/53LX6p75hOcCtAelMDyB8B"},{"number":"4","trackName":"Coltellata (feat. tha Supreme)","artist":"Gazzelle","streams":"192738","url":"https://open.spotify.com/track/6pswDYZetJz39k41bCXNif"},{"number":"5","trackName":"Venere e Marte (feat. Marco Mengoni, Frah Quintale)","artist":"Takagi & Ketra","streams":"183592","url":"https://open.spotify.com/track/4O3sAZoZDIhNRcfHNuU4Ps"},{"number":"6","trackName":"Non Fare Così","artist":"Capo Plaza","streams":"178022","url":"https://open.spotify.com/track/769M2rTiAoL7x2lKDHLjRa"},{"number":"7","trackName":"Scooby Doo","artist":"Pinguini Tattici Nucleari","streams":"170053","url":"https://open.spotify.com/track/1P6TlFb8EVH2nCX3luVpZW"},{"number":"8","trackName":"Ferma A Guardare (feat. Pinguini Tattici Nucleari)","artist":"Ernia","streams":"169745","url":"https://open.spotify.com/track/1eDC4NiUYgQSKpKDIvXxi4"},{"number":"9","trackName":"Save Your Tears","artist":"The Weeknd","streams":"158112","url":"https://open.spotify.com/track/5QO79kh1waicV47BqGRL3g"},{"number":"10","trackName":"Baby (with J Balvin)","artist":"Sfera Ebbasta","streams":"150302","url":"https://open.spotify.com/track/3eblNP3Zd5b5J3JaOckl8Y"}],"JP":[{"number":"1","trackName":"ドライフラワー","artist":"優里","streams":"375624","url":"https://open.spotify.com/track/7dH0dpi751EoguDDg3xx6J"},{"number":"2","trackName":"Dynamite","artist":"BTS","streams":"298175","url":"https://open.spotify.com/track/4saklk6nie3yiGePpBwUoc"},{"number":"3","trackName":"夜に駆ける","artist":"YOASOBI","streams":"274368","url":"https://open.spotify.com/track/6MCjmGYlw6mQVWRFVgBRvB"},{"number":"4","trackName":"うっせぇわ","artist":"Ado","streams":"265260","url":"https://open.spotify.com/track/6EzZn96uOc9JsVGNRpx06n"},{"number":"5","trackName":"怪物","artist":"YOASOBI","streams":"231067","url":"https://open.spotify.com/track/06XQvnJb53SUYmlWIhUXUi"},{"number":"6","trackName":"炎","artist":"LiSA","streams":"209264","url":"https://open.spotify.com/track/0cSkn2l67csUljEy0EEBPn"},{"number":"7","trackName":"群青","artist":"YOASOBI","streams":"196565","url":"https://open.spotify.com/track/1zd35Y44Blc1CwwVbW3Qnk"},{"number":"8","trackName":"勿忘","artist":"Awesome City Club","streams":"184135","url":"https://open.spotify.com/track/0XZyF9lv6diMt4bxThOL0h"},{"number":"9","trackName":"虹","artist":"Masaki Suda","streams":"181342","url":"https://open.spotify.com/track/7AIj86wFWqm7X1TZ2hzHwS"},{"number":"10","trackName":"Kaikai Kitan","artist":"Eve","streams":"178117","url":"https://open.spotify.com/track/6y4GYuZszeXNOXuBFsJlos"}],"LT":[{"number":"1","trackName":"Save Your Tears","artist":"The Weeknd","streams":"6084","url":"https://open.spotify.com/track/5QO79kh1waicV47BqGRL3g"},{"number":"2","trackName":"Discoteque","artist":"THE ROOP","streams":"5474","url":"https://open.spotify.com/track/7dMOzsTZOUtOF7W5kLN0gf"},{"number":"3","trackName":"drivers license","artist":"Olivia Rodrigo","streams":"4906","url":"https://open.spotify.com/track/7lPN2DXiMsVn7XUKtOW1CS"},{"number":"4","trackName":"Streets","artist":"Doja Cat","streams":"4134","url":"https://open.spotify.com/track/60ynsPSSKe6O3sfwRnIBRf"},{"number":"5","trackName":"The Business","artist":"Tiësto","streams":"3959","url":"https://open.spotify.com/track/6f3Slt0GbA2bPZlz0aIFXN"},{"number":"6","trackName":"Blinding Lights","artist":"The Weeknd","streams":"3377","url":"https://open.spotify.com/track/0VjIjW4GlUZAMYd2vXMi3b"},{"number":"7","trackName":"Calling My Phone","artist":"Lil Tjay","streams":"3278","url":"https://open.spotify.com/track/5Kskr9LcNYa0tpt5f0ZEJx"},{"number":"8","trackName":"Paradise (feat. Dermot Kennedy)","artist":"MEDUZA","streams":"3099","url":"https://open.spotify.com/track/6ft4hAq6yde8jPZY2i5zLr"},{"number":"9","trackName":"Tu Palauk","artist":"Justinas Jarutis","streams":"3079","url":"https://open.spotify.com/track/4krCTQAG6vHfMFsSBgNBY7"},{"number":"10","trackName":"Astronaut In The Ocean","artist":"Masked Wolf","streams":"2830","url":"https://open.spotify.com/track/3VT8hOC5vuDXBsHrR53WFh"}],"LU":[{"number":"1","trackName":"Blinding Lights","artist":"The Weeknd","streams":"3482","url":"https://open.spotify.com/track/0VjIjW4GlUZAMYd2vXMi3b"},{"number":"2","trackName":"Mood (feat. iann dior)","artist":"24kGoldn","streams":"3368","url":"https://open.spotify.com/track/3tjFYV6RSFtuktYl3ZtYcq"},{"number":"3","trackName":"Lemonade (feat. Gunna, Don Toliver & NAV)","artist":"Internet Money","streams":"2806","url":"https://open.spotify.com/track/7hxHWCCAIIxFLCzvDgnQHX"},{"number":"4","trackName":"Roses - Imanbek Remix","artist":"SAINt JHN","streams":"2276","url":"https://open.spotify.com/track/0zLCBJZSiELJf02ucPP9wb"},{"number":"5","trackName":"DÁKITI","artist":"Bad Bunny","streams":"2266","url":"https://open.spotify.com/track/4MzXwWMhyBbmu6hOcLVD49"},{"number":"6","trackName":"Head & Heart (feat. MNEK)","artist":"Joel Corry","streams":"2263","url":"https://open.spotify.com/track/6cx06DFPPHchuUAcTxznu9"},{"number":"7","trackName":"Dance Monkey","artist":"Tones And I","streams":"2228","url":"https://open.spotify.com/track/1rgnBhdG2JDFTbYkYRZAku"},{"number":"8","trackName":"Whoopty","artist":"CJ","streams":"2134","url":"https://open.spotify.com/track/5vGLcdRuSbUhD8ScwsGSdA"},{"number":"9","trackName":"positions","artist":"Ariana Grande","streams":"2025","url":"https://open.spotify.com/track/35mvY5S1H3J2QZyna3TFe0"},{"number":"10","trackName":"HOLIDAY","artist":"Lil Nas X","streams":"1979","url":"https://open.spotify.com/track/6zFMeegAMYQo0mt8rXtrli"}],"LV":[{"number":"1","trackName":"drivers license","artist":"Olivia Rodrigo","streams":"4639","url":"https://open.spotify.com/track/7lPN2DXiMsVn7XUKtOW1CS"},{"number":"2","trackName":"Save Your Tears","artist":"The Weeknd","streams":"3616","url":"https://open.spotify.com/track/5QO79kh1waicV47BqGRL3g"},{"number":"3","trackName":"Streets","artist":"Doja Cat","streams":"3561","url":"https://open.spotify.com/track/60ynsPSSKe6O3sfwRnIBRf"},{"number":"4","trackName":"Моя голова винтом","artist":"kostromin","streams":"3305","url":"https://open.spotify.com/track/4KrhaZm4JRkNO4HRdLvJIG"},{"number":"5","trackName":"Calling My Phone","artist":"Lil Tjay","streams":"3095","url":"https://open.spotify.com/track/5Kskr9LcNYa0tpt5f0ZEJx"},{"number":"6","trackName":"Astronaut In The Ocean","artist":"Masked Wolf","streams":"3095","url":"https://open.spotify.com/track/3VT8hOC5vuDXBsHrR53WFh"},{"number":"7","trackName":"The Business","artist":"Tiësto","streams":"2998","url":"https://open.spotify.com/track/6f3Slt0GbA2bPZlz0aIFXN"},{"number":"8","trackName":"Whoopty","artist":"CJ","streams":"2631","url":"https://open.spotify.com/track/5vGLcdRuSbUhD8ScwsGSdA"},{"number":"9","trackName":"WITHOUT YOU","artist":"The Kid LAROI","streams":"2603","url":"https://open.spotify.com/track/27OeeYzk6klgBh83TSvGMA"},{"number":"10","trackName":"Sweater Weather","artist":"The Neighbourhood","streams":"2525","url":"https://open.spotify.com/track/2QjOHCTQ1Jl3zawyYOpxh6"}],"MX":[{"number":"1","trackName":"DÁKITI","artist":"Bad Bunny","streams":"679156","url":"https://open.spotify.com/track/4MzXwWMhyBbmu6hOcLVD49"},{"number":"2","trackName":"BICHOTA","artist":"KAROL G","streams":"624803","url":"https://open.spotify.com/track/7vrJn5hDSXRmdXoR30KgF1"},{"number":"3","trackName":"Bandido","artist":"Myke Towers","streams":"523272","url":"https://open.spotify.com/track/1xK1Gg9SxG8fy2Ya373oqb"},{"number":"4","trackName":"LA NOCHE DE ANOCHE","artist":"Bad Bunny","streams":"475677","url":"https://open.spotify.com/track/2XIc1pqjXV3Cr2BQUGNBck"},{"number":"5","trackName":"Save Your Tears","artist":"The Weeknd","streams":"433728","url":"https://open.spotify.com/track/5QO79kh1waicV47BqGRL3g"},{"number":"6","trackName":"Hawái","artist":"Maluma","streams":"387271","url":"https://open.spotify.com/track/1yoMvmasuxZfqHEipJhRbp"},{"number":"7","trackName":"Ropa Cara","artist":"Camilo","streams":"384551","url":"https://open.spotify.com/track/7BIy3EGQhg98CsRdKYHnJC"},{"number":"8","trackName":"Reloj","artist":"Rauw Alejandro","streams":"365167","url":"https://open.spotify.com/track/4loQgPwJHocL3dFwLfjb1J"},{"number":"9","trackName":"Baila Conmigo (with Rauw Alejandro)","artist":"Selena Gomez","streams":"346608","url":"https://open.spotify.com/track/0D75ciM842cdUMKSMfAR9y"},{"number":"10","trackName":"Blinding Lights","artist":"The Weeknd","streams":"340793","url":"https://open.spotify.com/track/0VjIjW4GlUZAMYd2vXMi3b"}],"MY":[{"number":"1","trackName":"drivers license","artist":"Olivia Rodrigo","streams":"55953","url":"https://open.spotify.com/track/7lPN2DXiMsVn7XUKtOW1CS"},{"number":"2","trackName":"At My Worst","artist":"Pink Sweat$","streams":"46048","url":"https://open.spotify.com/track/2MJz8BxxMsERULatmBikDH"},{"number":"3","trackName":"HEARTBREAK ANNIVERSARY","artist":"Giveon","streams":"43376","url":"https://open.spotify.com/track/3FAJ6O0NOHQV8Mc5Ri6ENp"},{"number":"4","trackName":"Save Your Tears","artist":"The Weeknd","streams":"35552","url":"https://open.spotify.com/track/5QO79kh1waicV47BqGRL3g"},{"number":"5","trackName":"Life Goes On","artist":"BTS","streams":"30938","url":"https://open.spotify.com/track/249gnXrbfmV8NG6jTEMSwD"},{"number":"6","trackName":"Mungkin Hari Ini Esok Atau Nanti","artist":"Anneth","streams":"28861","url":"https://open.spotify.com/track/7n5nvulc1oW1ErpeTrNezI"},{"number":"7","trackName":"you broke me first","artist":"Tate McRae","streams":"27955","url":"https://open.spotify.com/track/45bE4HXI0AwGZXfZtMp8JR"},{"number":"8","trackName":"Heather","artist":"Conan Gray","streams":"27865","url":"https://open.spotify.com/track/4xqrdfXkTW4T0RauPLv3WA"},{"number":"9","trackName":"34+35","artist":"Ariana Grande","streams":"26851","url":"https://open.spotify.com/track/6Im9k8u9iIzKMrmV7BWtlF"},{"number":"10","trackName":"positions","artist":"Ariana Grande","streams":"26656","url":"https://open.spotify.com/track/35mvY5S1H3J2QZyna3TFe0"}],"NI":[{"number":"1","trackName":"DÁKITI","artist":"Bad Bunny","streams":"9068","url":"https://open.spotify.com/track/4MzXwWMhyBbmu6hOcLVD49"},{"number":"2","trackName":"LA NOCHE DE ANOCHE","artist":"Bad Bunny","streams":"7143","url":"https://open.spotify.com/track/2XIc1pqjXV3Cr2BQUGNBck"},{"number":"3","trackName":"Bandido","artist":"Myke Towers","streams":"7122","url":"https://open.spotify.com/track/1xK1Gg9SxG8fy2Ya373oqb"},{"number":"4","trackName":"BICHOTA","artist":"KAROL G","streams":"5497","url":"https://open.spotify.com/track/7vrJn5hDSXRmdXoR30KgF1"},{"number":"5","trackName":"BOOKER T","artist":"Bad Bunny","streams":"5071","url":"https://open.spotify.com/track/26w9NTiE9NGjW1ZvIOd1So"},{"number":"6","trackName":"Hecha Pa' Mi","artist":"Boza","streams":"4663","url":"https://open.spotify.com/track/3VvA1wSxukMLsvXoXtlwWx"},{"number":"7","trackName":"Hawái","artist":"Maluma","streams":"4352","url":"https://open.spotify.com/track/1yoMvmasuxZfqHEipJhRbp"},{"number":"8","trackName":"Reloj","artist":"Rauw Alejandro","streams":"4250","url":"https://open.spotify.com/track/4loQgPwJHocL3dFwLfjb1J"},{"number":"9","trackName":"TE MUDASTE","artist":"Bad Bunny","streams":"4192","url":"https://open.spotify.com/track/5RubKOuDoPn5Kj5TLVxSxY"},{"number":"10","trackName":"Chica Ideal","artist":"Sebastian Yatra","streams":"4115","url":"https://open.spotify.com/track/21N4Buj4xsyLb218lYle61"}],"NL":[{"number":"1","trackName":"drivers license","artist":"Olivia Rodrigo","streams":"218652","url":"https://open.spotify.com/track/7lPN2DXiMsVn7XUKtOW1CS"},{"number":"2","trackName":"Wellerman - Sea Shanty / 220 KID x Billen Ted Remix","artist":"Nathan Evans","streams":"163077","url":"https://open.spotify.com/track/3iw6V4LH7yPj1ESORX9RIN"},{"number":"3","trackName":"WITHOUT YOU","artist":"The Kid LAROI","streams":"161957","url":"https://open.spotify.com/track/27OeeYzk6klgBh83TSvGMA"},{"number":"4","trackName":"The Business","artist":"Tiësto","streams":"144605","url":"https://open.spotify.com/track/6f3Slt0GbA2bPZlz0aIFXN"},{"number":"5","trackName":"Nu Wij Niet Meer Praten","artist":"Jaap Reesema","streams":"141639","url":"https://open.spotify.com/track/13UfB1tm7QYrhtW8FhPYmW"},{"number":"6","trackName":"Als Ik Je Weer Zie","artist":"Thomas Acda","streams":"129735","url":"https://open.spotify.com/track/3yraHvsUkmnJjGhOrx1CSg"},{"number":"7","trackName":"All We Got (feat. KIDDO)","artist":"Robin Schulz","streams":"116329","url":"https://open.spotify.com/track/1FP9s72rDYty6mfoOEYKnE"},{"number":"8","trackName":"Love Not War (The Tampa Beat)","artist":"Jason Derulo","streams":"112230","url":"https://open.spotify.com/track/4Lt6GXGzYsa1tgkv3nGSTm"},{"number":"9","trackName":"Anyone","artist":"Justin Bieber","streams":"107623","url":"https://open.spotify.com/track/31qCy5ZaophVA81wtlwLc4"},{"number":"10","trackName":"Paradise (feat. Dermot Kennedy)","artist":"MEDUZA","streams":"105464","url":"https://open.spotify.com/track/6ft4hAq6yde8jPZY2i5zLr"}],"NO":[{"number":"1","trackName":"Jeg glemmer deg aldri - fra Rådebank","artist":"Emma Steinbakken","streams":"135480","url":"https://open.spotify.com/track/1oKXshzJtz3zDA6dJY8VlZ"},{"number":"2","trackName":"drivers license","artist":"Olivia Rodrigo","streams":"107827","url":"https://open.spotify.com/track/7lPN2DXiMsVn7XUKtOW1CS"},{"number":"3","trackName":"Calling My Phone","artist":"Lil Tjay","streams":"80505","url":"https://open.spotify.com/track/5Kskr9LcNYa0tpt5f0ZEJx"},{"number":"4","trackName":"I Need a Man","artist":"Hver gang vi møtes","streams":"77171","url":"https://open.spotify.com/track/3CjgnAIAtDSpabk4WxU5Tq"},{"number":"5","trackName":"Save Your Tears","artist":"The Weeknd","streams":"76339","url":"https://open.spotify.com/track/5QO79kh1waicV47BqGRL3g"},{"number":"6","trackName":"Sju Fjell","artist":"El Papi","streams":"72462","url":"https://open.spotify.com/track/04k0QThdHEp7kg3FpXVh0Q"},{"number":"7","trackName":"WITHOUT YOU","artist":"The Kid LAROI","streams":"71726","url":"https://open.spotify.com/track/27OeeYzk6klgBh83TSvGMA"},{"number":"8","trackName":"Wellerman - Sea Shanty / 220 KID x Billen Ted Remix","artist":"Nathan Evans","streams":"65874","url":"https://open.spotify.com/track/3iw6V4LH7yPj1ESORX9RIN"},{"number":"9","trackName":"Ut Av Mørket","artist":"TIX","streams":"62617","url":"https://open.spotify.com/track/4ztkWLky8oMwqu2fSLRfwg"},{"number":"10","trackName":"Astronaut In The Ocean","artist":"Masked Wolf","streams":"59813","url":"https://open.spotify.com/track/3VT8hOC5vuDXBsHrR53WFh"}],"NZ":[{"number":"1","trackName":"drivers license","artist":"Olivia Rodrigo","streams":"51501","url":"https://open.spotify.com/track/7lPN2DXiMsVn7XUKtOW1CS"},{"number":"2","trackName":"Calling My Phone","artist":"Lil Tjay","streams":"38383","url":"https://open.spotify.com/track/5Kskr9LcNYa0tpt5f0ZEJx"},{"number":"3","trackName":"Good Days","artist":"SZA","streams":"31002","url":"https://open.spotify.com/track/3YJJjQPAbDT7mGpX3WtQ9A"},{"number":"4","trackName":"Why Oh Why","artist":"L.A.B.","streams":"28676","url":"https://open.spotify.com/track/3TaGtHDHWQ7TfPpX0eJrtB"},{"number":"5","trackName":"WITHOUT YOU","artist":"The Kid LAROI","streams":"28078","url":"https://open.spotify.com/track/27OeeYzk6klgBh83TSvGMA"},{"number":"6","trackName":"Not My Neighbour","artist":"Niko Walters","streams":"27576","url":"https://open.spotify.com/track/2Tf3a4gkBbrN2UbMNbwtdQ"},{"number":"7","trackName":"Heat Waves","artist":"Glass Animals","streams":"26873","url":"https://open.spotify.com/track/02MWAaffLxlfxAUY7c5dvx"},{"number":"8","trackName":"Controller","artist":"L.A.B.","streams":"25387","url":"https://open.spotify.com/track/2DkxWMmdvS3f5hbz4UGQLO"},{"number":"9","trackName":"Streets","artist":"Doja Cat","streams":"23849","url":"https://open.spotify.com/track/60ynsPSSKe6O3sfwRnIBRf"},{"number":"10","trackName":"In The Air","artist":"L.A.B.","streams":"23493","url":"https://open.spotify.com/track/4d2tgzpNhQO8HIxC4YLnBe"}],"PA":[{"number":"1","trackName":"Bandido","artist":"Myke Towers","streams":"22482","url":"https://open.spotify.com/track/1xK1Gg9SxG8fy2Ya373oqb"},{"number":"2","trackName":"DÁKITI","artist":"Bad Bunny","streams":"21514","url":"https://open.spotify.com/track/4MzXwWMhyBbmu6hOcLVD49"},{"number":"3","trackName":"Hecha Pa' Mi","artist":"Boza","streams":"19775","url":"https://open.spotify.com/track/3VvA1wSxukMLsvXoXtlwWx"},{"number":"4","trackName":"911","artist":"Sech","streams":"19249","url":"https://open.spotify.com/track/2TksvaRivgAEj780DgRB73"},{"number":"5","trackName":"LA NOCHE DE ANOCHE","artist":"Bad Bunny","streams":"17393","url":"https://open.spotify.com/track/2XIc1pqjXV3Cr2BQUGNBck"},{"number":"6","trackName":"Follie Flow","artist":"Italian Somali","streams":"15193","url":"https://open.spotify.com/track/5HJAOnMn4sXWlLwDFf0eCH"},{"number":"7","trackName":"BICHOTA","artist":"KAROL G","streams":"14956","url":"https://open.spotify.com/track/7vrJn5hDSXRmdXoR30KgF1"},{"number":"8","trackName":"La Nota","artist":"Manuel Turizo","streams":"13028","url":"https://open.spotify.com/track/7ndTONDDRFGiPnnhOzOXxq"},{"number":"9","trackName":"Reloj","artist":"Rauw Alejandro","streams":"12445","url":"https://open.spotify.com/track/4loQgPwJHocL3dFwLfjb1J"},{"number":"10","trackName":"Otra Baby","artist":"Akim","streams":"11213","url":"https://open.spotify.com/track/4f2nbpKWfnj7tNyL2Ihj9n"}],"PE":[{"number":"1","trackName":"Bandido","artist":"Myke Towers","streams":"133165","url":"https://open.spotify.com/track/1xK1Gg9SxG8fy2Ya373oqb"},{"number":"2","trackName":"DÁKITI","artist":"Bad Bunny","streams":"101659","url":"https://open.spotify.com/track/4MzXwWMhyBbmu6hOcLVD49"},{"number":"3","trackName":"LA NOCHE DE ANOCHE","artist":"Bad Bunny","streams":"101103","url":"https://open.spotify.com/track/2XIc1pqjXV3Cr2BQUGNBck"},{"number":"4","trackName":"Hecha Pa' Mi","artist":"Boza","streams":"96680","url":"https://open.spotify.com/track/3VvA1wSxukMLsvXoXtlwWx"},{"number":"5","trackName":"BICHOTA","artist":"KAROL G","streams":"95288","url":"https://open.spotify.com/track/7vrJn5hDSXRmdXoR30KgF1"},{"number":"6","trackName":"Reloj","artist":"Rauw Alejandro","streams":"84886","url":"https://open.spotify.com/track/4loQgPwJHocL3dFwLfjb1J"},{"number":"7","trackName":"Baila Conmigo (with Rauw Alejandro)","artist":"Selena Gomez","streams":"76171","url":"https://open.spotify.com/track/0D75ciM842cdUMKSMfAR9y"},{"number":"8","trackName":"No Te Enamores - Remix","artist":"Milly","streams":"71224","url":"https://open.spotify.com/track/2mM3gZ0BbPwPPMelbA8vgt"},{"number":"9","trackName":"Chica Ideal","artist":"Sebastian Yatra","streams":"66312","url":"https://open.spotify.com/track/21N4Buj4xsyLb218lYle61"},{"number":"10","trackName":"BEBÉ","artist":"Camilo","streams":"65408","url":"https://open.spotify.com/track/7D7EH7MGyNHWSkqrszerI1"}],"PH":[{"number":"1","trackName":"HEARTBREAK ANNIVERSARY","artist":"Giveon","streams":"309354","url":"https://open.spotify.com/track/3FAJ6O0NOHQV8Mc5Ri6ENp"},{"number":"2","trackName":"Paubaya","artist":"Moira Dela Torre","streams":"270881","url":"https://open.spotify.com/track/1NUw61RX4Wtmxw7CLiP4kP"},{"number":"3","trackName":"drivers license","artist":"Olivia Rodrigo","streams":"266890","url":"https://open.spotify.com/track/7lPN2DXiMsVn7XUKtOW1CS"},{"number":"4","trackName":"At My Worst","artist":"Pink Sweat$","streams":"216206","url":"https://open.spotify.com/track/2MJz8BxxMsERULatmBikDH"},{"number":"5","trackName":"Dance With You","artist":"Skusta Clee","streams":"181066","url":"https://open.spotify.com/track/7bUvgvAf0tdQIty95lV5wf"},{"number":"6","trackName":"Panalo (Trap Cariñosa)","artist":"Ez Mil","streams":"152850","url":"https://open.spotify.com/track/5J0obeHgIFKkPiGBPTOqLw"},{"number":"7","trackName":"Copines","artist":"Aya Nakamura","streams":"152143","url":"https://open.spotify.com/track/1Bhm5HNO1cq8olDbBmokyL"},{"number":"8","trackName":"34+35","artist":"Ariana Grande","streams":"152037","url":"https://open.spotify.com/track/6Im9k8u9iIzKMrmV7BWtlF"},{"number":"9","trackName":"Dynamite","artist":"BTS","streams":"148783","url":"https://open.spotify.com/track/4saklk6nie3yiGePpBwUoc"},{"number":"10","trackName":"Love Story (Taylor’s Version)","artist":"Taylor Swift","streams":"140831","url":"https://open.spotify.com/track/3CeCwYWvdfXbZLXFhBrbnf"}],"PL":[{"number":"1","trackName":"Szklanki","artist":"Young Leosia","streams":"123979","url":"https://open.spotify.com/track/7umEhzfURpGTSRbcX84qLy"},{"number":"2","trackName":"Ale jazz!","artist":"sanah","streams":"103226","url":"https://open.spotify.com/track/7fuvhZxxLou4qRRo4Z63wE"},{"number":"3","trackName":"BLUEBERRY","artist":"Guzior","streams":"95434","url":"https://open.spotify.com/track/27gknDBOqYJmOFYyaOBAfa"},{"number":"4","trackName":"drivers license","artist":"Olivia Rodrigo","streams":"90168","url":"https://open.spotify.com/track/7lPN2DXiMsVn7XUKtOW1CS"},{"number":"5","trackName":"FALA","artist":"Guzior","streams":"79646","url":"https://open.spotify.com/track/4XZxxP6ilbl56BooNjq7Ki"},{"number":"6","trackName":"Save Your Tears","artist":"The Weeknd","streams":"77014","url":"https://open.spotify.com/track/5QO79kh1waicV47BqGRL3g"},{"number":"7","trackName":"OBOK","artist":"Żabson","streams":"75725","url":"https://open.spotify.com/track/1YYyfjeqq910iiPShYlAYj"},{"number":"8","trackName":"Testarossa","artist":"Wiatr","streams":"64574","url":"https://open.spotify.com/track/4yP4P2pHqtejjQ1l12J8bA"},{"number":"9","trackName":"Mam Na Twarzy Krew I Tym Razem Nie Jest Sztuczna","artist":"Chivas","streams":"60145","url":"https://open.spotify.com/track/26N0AElCFxUuGQ7YoYs0tU"},{"number":"10","trackName":"The Business","artist":"Tiësto","streams":"60122","url":"https://open.spotify.com/track/6f3Slt0GbA2bPZlz0aIFXN"}],"PT":[{"number":"1","trackName":"drivers license","artist":"Olivia Rodrigo","streams":"31304","url":"https://open.spotify.com/track/7lPN2DXiMsVn7XUKtOW1CS"},{"number":"2","trackName":"Mds","artist":"Kawe","streams":"23158","url":"https://open.spotify.com/track/0QglpM23kl9ldvVdoYNZwF"},{"number":"3","trackName":"Borboletas","artist":"Gama WNTD","streams":"21409","url":"https://open.spotify.com/track/3AroFQ5v6wHUOqwpGZw3OW"},{"number":"4","trackName":"Perseus","artist":"Wet Bed Gang","streams":"21277","url":"https://open.spotify.com/track/21tsJFuHp7gqkyY1Qg9vmD"},{"number":"5","trackName":"Blinding Lights","artist":"The Weeknd","streams":"20909","url":"https://open.spotify.com/track/0VjIjW4GlUZAMYd2vXMi3b"},{"number":"6","trackName":"Calling My Phone","artist":"Lil Tjay","streams":"20762","url":"https://open.spotify.com/track/5Kskr9LcNYa0tpt5f0ZEJx"},{"number":"7","trackName":"Save Your Tears","artist":"The Weeknd","streams":"20615","url":"https://open.spotify.com/track/5QO79kh1waicV47BqGRL3g"},{"number":"8","trackName":"inesquecível","artist":"Giulia Be","streams":"20372","url":"https://open.spotify.com/track/3bUDPTCStUeLcUgXgvepQh"},{"number":"9","trackName":"WITHOUT YOU","artist":"The Kid LAROI","streams":"20282","url":"https://open.spotify.com/track/27OeeYzk6klgBh83TSvGMA"},{"number":"10","trackName":"São Paulo","artist":"Yuri NR5","streams":"20062","url":"https://open.spotify.com/track/20cn2KYYgyuxXRC3WynYZn"}],"PY":[{"number":"1","trackName":"Bandido","artist":"Myke Towers","streams":"63116","url":"https://open.spotify.com/track/1xK1Gg9SxG8fy2Ya373oqb"},{"number":"2","trackName":"LA NOCHE DE ANOCHE","artist":"Bad Bunny","streams":"50616","url":"https://open.spotify.com/track/2XIc1pqjXV3Cr2BQUGNBck"},{"number":"3","trackName":"DÁKITI","artist":"Bad Bunny","streams":"46259","url":"https://open.spotify.com/track/4MzXwWMhyBbmu6hOcLVD49"},{"number":"4","trackName":"Hecha Pa' Mi","artist":"Boza","streams":"41169","url":"https://open.spotify.com/track/3VvA1wSxukMLsvXoXtlwWx"},{"number":"5","trackName":"BICHOTA","artist":"KAROL G","streams":"40673","url":"https://open.spotify.com/track/7vrJn5hDSXRmdXoR30KgF1"},{"number":"6","trackName":"Reloj","artist":"Rauw Alejandro","streams":"37700","url":"https://open.spotify.com/track/4loQgPwJHocL3dFwLfjb1J"},{"number":"7","trackName":"Polvo","artist":"Nicky Jam","streams":"35601","url":"https://open.spotify.com/track/68mrW6gXHgupgSiDHgaDi5"},{"number":"8","trackName":"Hasta Abajo","artist":"Kevin Roldan","streams":"33941","url":"https://open.spotify.com/track/4PEfJZpVjdclfzZ9XO8uDw"},{"number":"9","trackName":"La Nota","artist":"Manuel Turizo","streams":"33404","url":"https://open.spotify.com/track/7ndTONDDRFGiPnnhOzOXxq"},{"number":"10","trackName":"Baila Conmigo (with Rauw Alejandro)","artist":"Selena Gomez","streams":"29345","url":"https://open.spotify.com/track/0D75ciM842cdUMKSMfAR9y"}],"RO":[{"number":"1","trackName":"Astronaut In The Ocean","artist":"Masked Wolf","streams":"11546","url":"https://open.spotify.com/track/3VT8hOC5vuDXBsHrR53WFh"},{"number":"2","trackName":"drivers license","artist":"Olivia Rodrigo","streams":"9449","url":"https://open.spotify.com/track/7lPN2DXiMsVn7XUKtOW1CS"},{"number":"3","trackName":"Calling My Phone","artist":"Lil Tjay","streams":"9040","url":"https://open.spotify.com/track/5Kskr9LcNYa0tpt5f0ZEJx"},{"number":"4","trackName":"The Business","artist":"Tiësto","streams":"8437","url":"https://open.spotify.com/track/6f3Slt0GbA2bPZlz0aIFXN"},{"number":"5","trackName":"Save Your Tears","artist":"The Weeknd","streams":"8315","url":"https://open.spotify.com/track/5QO79kh1waicV47BqGRL3g"},{"number":"6","trackName":"Whoopty","artist":"CJ","streams":"7900","url":"https://open.spotify.com/track/5vGLcdRuSbUhD8ScwsGSdA"},{"number":"7","trackName":"Streets","artist":"Doja Cat","streams":"7786","url":"https://open.spotify.com/track/60ynsPSSKe6O3sfwRnIBRf"},{"number":"8","trackName":"Blinding Lights","artist":"The Weeknd","streams":"7633","url":"https://open.spotify.com/track/0VjIjW4GlUZAMYd2vXMi3b"},{"number":"9","trackName":"Lemonade (feat. Gunna, Don Toliver & NAV)","artist":"Internet Money","streams":"6674","url":"https://open.spotify.com/track/7hxHWCCAIIxFLCzvDgnQHX"},{"number":"10","trackName":"Savana","artist":"Marko Glass","streams":"6655","url":"https://open.spotify.com/track/4BJsV9Iu4sJphgvAyDxfkp"}],"RU":[{"number":"1","trackName":"Моя голова винтом","artist":"kostromin","streams":"64570","url":"https://open.spotify.com/track/4KrhaZm4JRkNO4HRdLvJIG"},{"number":"2","trackName":"Cristal & МОЁТ","artist":"MORGENSHTERN","streams":"55118","url":"https://open.spotify.com/track/4KfmruShP5zOi9hYjM76e6"},{"number":"3","trackName":"Чистый - OST «Псих»","artist":"Scriptonite","streams":"44391","url":"https://open.spotify.com/track/2Z0OcpA4i1KayJbXn800le"},{"number":"4","trackName":"Astronaut In The Ocean","artist":"Masked Wolf","streams":"43505","url":"https://open.spotify.com/track/3VT8hOC5vuDXBsHrR53WFh"},{"number":"5","trackName":"Camry 3.5","artist":"UncleFlexxx","streams":"42893","url":"https://open.spotify.com/track/4qTNag73xHeQLFF5fEJWUQ"},{"number":"6","trackName":"Снова я напиваюсь","artist":"SLAVA MARLOW","streams":"41279","url":"https://open.spotify.com/track/18t2lAzaHW2bJomYeyzrpy"},{"number":"7","trackName":"Бумеранг","artist":"Markul","streams":"40298","url":"https://open.spotify.com/track/2tZdQQAd8TPdHo86nLM0q3"},{"number":"8","trackName":"KARI","artist":"Big Baby Tape","streams":"37309","url":"https://open.spotify.com/track/5qhdXxsc1l7hQHOc1aZaGn"},{"number":"9","trackName":"Дежавю","artist":"kizaru","streams":"36868","url":"https://open.spotify.com/track/1GOiMxQXZUzjzH0Sxpck0B"},{"number":"10","trackName":"Кукла колдуна","artist":"Korol i Shut","streams":"35818","url":"https://open.spotify.com/track/2DYzsMQpO7xOw7b3JwyIWP"}],"SE":[{"number":"1","trackName":"tystnar i luren","artist":"Miriam Bryant","streams":"263682","url":"https://open.spotify.com/track/4dxeRrYgeAQ1F0uH9g04lN"},{"number":"2","trackName":"Barn av vår tid","artist":"Hov1","streams":"157371","url":"https://open.spotify.com/track/09ZI6ytqLZe1sRXLKPKZNe"},{"number":"3","trackName":"Du måste finnas","artist":"Newkid","streams":"131760","url":"https://open.spotify.com/track/32z2QHVJTOPzzczl4MjmHo"},{"number":"4","trackName":"drivers license","artist":"Olivia Rodrigo","streams":"127366","url":"https://open.spotify.com/track/7lPN2DXiMsVn7XUKtOW1CS"},{"number":"5","trackName":"Sätter Dom På Plats","artist":"Einár","streams":"99231","url":"https://open.spotify.com/track/6tTZfzCuQxamzX7DlNC0hh"},{"number":"6","trackName":"Jerusalema (feat. Nomcebo Zikode)","artist":"Master KG","streams":"98022","url":"https://open.spotify.com/track/2MlOUXmcofMackX3bxfSwi"},{"number":"7","trackName":"Svag","artist":"Victor Leksell","streams":"97079","url":"https://open.spotify.com/track/4SS4YfDAEQG0fZAe1xfgn3"},{"number":"8","trackName":"Starkare","artist":"Newkid","streams":"94333","url":"https://open.spotify.com/track/1KaddVS6HXYrvt6ETZtRQ8"},{"number":"9","trackName":"Save Your Tears","artist":"The Weeknd","streams":"94209","url":"https://open.spotify.com/track/5QO79kh1waicV47BqGRL3g"},{"number":"10","trackName":"ICE","artist":"Ricky Rich","streams":"90899","url":"https://open.spotify.com/track/2vTin2H3idCl2nuc3CqdPR"}],"SG":[{"number":"1","trackName":"drivers license","artist":"Olivia Rodrigo","streams":"54567","url":"https://open.spotify.com/track/7lPN2DXiMsVn7XUKtOW1CS"},{"number":"2","trackName":"At My Worst","artist":"Pink Sweat$","streams":"37289","url":"https://open.spotify.com/track/2MJz8BxxMsERULatmBikDH"},{"number":"3","trackName":"Save Your Tears","artist":"The Weeknd","streams":"35877","url":"https://open.spotify.com/track/5QO79kh1waicV47BqGRL3g"},{"number":"4","trackName":"Celebrity","artist":"IU","streams":"31128","url":"https://open.spotify.com/track/4RewTiGEGoO7FWNZUmp1f4"},{"number":"5","trackName":"HEARTBREAK ANNIVERSARY","artist":"Giveon","streams":"29885","url":"https://open.spotify.com/track/3FAJ6O0NOHQV8Mc5Ri6ENp"},{"number":"6","trackName":"刻在我心底的名字 (Your Name Engraved Herein) - 電影<刻在你心底的名字>主題曲","artist":"Crowd Lu","streams":"25440","url":"https://open.spotify.com/track/3OC84eKMxRJ4x0Hcwl9i4i"},{"number":"7","trackName":"Love Story (Taylor’s Version)","artist":"Taylor Swift","streams":"24185","url":"https://open.spotify.com/track/3CeCwYWvdfXbZLXFhBrbnf"},{"number":"8","trackName":"34+35","artist":"Ariana Grande","streams":"23693","url":"https://open.spotify.com/track/6Im9k8u9iIzKMrmV7BWtlF"},{"number":"9","trackName":"positions","artist":"Ariana Grande","streams":"23006","url":"https://open.spotify.com/track/35mvY5S1H3J2QZyna3TFe0"},{"number":"10","trackName":"飞鸟和蝉","artist":"Ren Ran","streams":"22533","url":"https://open.spotify.com/track/3IveWAHTMxZA4KYBPnylq5"}],"SK":[{"number":"1","trackName":"Astronaut In The Ocean","artist":"Masked Wolf","streams":"11066","url":"https://open.spotify.com/track/3VT8hOC5vuDXBsHrR53WFh"},{"number":"2","trackName":"The Business","artist":"Tiësto","streams":"7671","url":"https://open.spotify.com/track/6f3Slt0GbA2bPZlz0aIFXN"},{"number":"3","trackName":"drivers license","artist":"Olivia Rodrigo","streams":"7632","url":"https://open.spotify.com/track/7lPN2DXiMsVn7XUKtOW1CS"},{"number":"4","trackName":"Paradise (feat. Dermot Kennedy)","artist":"MEDUZA","streams":"6200","url":"https://open.spotify.com/track/6ft4hAq6yde8jPZY2i5zLr"},{"number":"5","trackName":"Save Your Tears","artist":"The Weeknd","streams":"6068","url":"https://open.spotify.com/track/5QO79kh1waicV47BqGRL3g"},{"number":"6","trackName":"Rodinnej Typ","artist":"Yzomandias","streams":"5962","url":"https://open.spotify.com/track/35nvMkQglkoeydD81a0b77"},{"number":"7","trackName":"Mood (feat. iann dior)","artist":"24kGoldn","streams":"5863","url":"https://open.spotify.com/track/3tjFYV6RSFtuktYl3ZtYcq"},{"number":"8","trackName":"Blinding Lights","artist":"The Weeknd","streams":"5204","url":"https://open.spotify.com/track/0VjIjW4GlUZAMYd2vXMi3b"},{"number":"9","trackName":"Whoopty","artist":"CJ","streams":"5200","url":"https://open.spotify.com/track/5vGLcdRuSbUhD8ScwsGSdA"},{"number":"10","trackName":"BodyBag","artist":"Yzomandias","streams":"5153","url":"https://open.spotify.com/track/3fBpzO81OXrmZPKL0KG8LF"}],"SV":[{"number":"1","trackName":"DÁKITI","artist":"Bad Bunny","streams":"23670","url":"https://open.spotify.com/track/4MzXwWMhyBbmu6hOcLVD49"},{"number":"2","trackName":"Bandido","artist":"Myke Towers","streams":"23176","url":"https://open.spotify.com/track/1xK1Gg9SxG8fy2Ya373oqb"},{"number":"3","trackName":"LA NOCHE DE ANOCHE","artist":"Bad Bunny","streams":"18487","url":"https://open.spotify.com/track/2XIc1pqjXV3Cr2BQUGNBck"},{"number":"4","trackName":"BICHOTA","artist":"KAROL G","streams":"17851","url":"https://open.spotify.com/track/7vrJn5hDSXRmdXoR30KgF1"},{"number":"5","trackName":"Reloj","artist":"Rauw Alejandro","streams":"16293","url":"https://open.spotify.com/track/4loQgPwJHocL3dFwLfjb1J"},{"number":"6","trackName":"Hecha Pa' Mi","artist":"Boza","streams":"14259","url":"https://open.spotify.com/track/3VvA1wSxukMLsvXoXtlwWx"},{"number":"7","trackName":"Hawái","artist":"Maluma","streams":"11708","url":"https://open.spotify.com/track/1yoMvmasuxZfqHEipJhRbp"},{"number":"8","trackName":"TE MUDASTE","artist":"Bad Bunny","streams":"11626","url":"https://open.spotify.com/track/5RubKOuDoPn5Kj5TLVxSxY"},{"number":"9","trackName":"La Nota","artist":"Manuel Turizo","streams":"11606","url":"https://open.spotify.com/track/7ndTONDDRFGiPnnhOzOXxq"},{"number":"10","trackName":"Hasta Abajo","artist":"Kevin Roldan","streams":"11503","url":"https://open.spotify.com/track/4PEfJZpVjdclfzZ9XO8uDw"}],"TH":[{"number":"1","trackName":"Extraordinary","artist":"Anatomy Rabbit","streams":"68648","url":"https://open.spotify.com/track/19CoWVqDyUbiqxoyMf4HkJ"},{"number":"2","trackName":"ถ้าเธอรักฉันจริง","artist":"Three Man Down","streams":"62387","url":"https://open.spotify.com/track/2vA7CHG08LDzeMDAuPnUQg"},{"number":"3","trackName":"จำเลยรัก - Defendant Of Love","artist":"F.HERO","streams":"59373","url":"https://open.spotify.com/track/0AGhwXsWpVOwjHY5yf4dtD"},{"number":"4","trackName":"จีบ","artist":"Qler","streams":"51212","url":"https://open.spotify.com/track/5bvgLLWn7IFu6mOa46XaoV"},{"number":"5","trackName":"ช่วยไม่ได้","artist":"UrboyTJ","streams":"45557","url":"https://open.spotify.com/track/4GGNl8jiANylTJj4hfzqP7"},{"number":"6","trackName":"Roses","artist":"Finn Askew","streams":"43004","url":"https://open.spotify.com/track/7h5JV2j5wEwMP2hQE12Nk4"},{"number":"7","trackName":"แค่ฝันไป","artist":"Whal & Dolph","streams":"42635","url":"https://open.spotify.com/track/6odrQWsbCEeOZ8gptITc2i"},{"number":"8","trackName":"โคตรพิเศษ - (Ost. แปลรักฉันด้วยใจเธอ)","artist":"Billkin","streams":"42011","url":"https://open.spotify.com/track/6MVbuOWvXHbPHtVwScK6M1"},{"number":"9","trackName":"At My Worst","artist":"Pink Sweat$","streams":"41379","url":"https://open.spotify.com/track/2MJz8BxxMsERULatmBikDH"},{"number":"10","trackName":"แฟนใหม่หน้าคุ้น","artist":"Maiyarap","streams":"40031","url":"https://open.spotify.com/track/29E8BUUDQbc5S7jMPOj9wW"}],"TR":[{"number":"1","trackName":"Astronaut In The Ocean","artist":"Masked Wolf","streams":"168103","url":"https://open.spotify.com/track/3VT8hOC5vuDXBsHrR53WFh"},{"number":"2","trackName":"Seni Dert Etmeler","artist":"Madrigal","streams":"162973","url":"https://open.spotify.com/track/10n66m41IGjA2ZulKPK7Ew"},{"number":"3","trackName":"Kusura Bakma","artist":"Tuğkan","streams":"139183","url":"https://open.spotify.com/track/7ng3MkDXpSUVFQEhN6vtqG"},{"number":"4","trackName":"Makina","artist":"UZI","streams":"130213","url":"https://open.spotify.com/track/2huQiKGkgUfp4WjnVRSobL"},{"number":"5","trackName":"B.S.G.","artist":"BEGE","streams":"122969","url":"https://open.spotify.com/track/5KvWAPJDBNXzy5l1bywB7x"},{"number":"6","trackName":"ıslak kum","artist":"Contra","streams":"121629","url":"https://open.spotify.com/track/3XeMdSHi48X0XsDHckDhIM"},{"number":"7","trackName":"Seni Öptüğüm Sokak","artist":"Tuğçe Kandemir","streams":"109510","url":"https://open.spotify.com/track/1pgSJ8yNeLCqyrCeix7caQ"},{"number":"8","trackName":"Zemin","artist":"Emir Can İğrek","streams":"108625","url":"https://open.spotify.com/track/5WT3ohLdg04eUy9Bz2sRsi"},{"number":"9","trackName":"Bir Sebebi Var","artist":"İkilem","streams":"108306","url":"https://open.spotify.com/track/4WixufiyHUgg1jFqkYop2K"},{"number":"10","trackName":"Uzaklara Savrulalım","artist":"Perdenin Ardındakiler","streams":"105668","url":"https://open.spotify.com/track/7LGuxwQ3PzCxtinavcMlew"}],"TW":[{"number":"1","trackName":"刻在我心底的名字 (Your Name Engraved Herein) - 電影<刻在你心底的名字>主題曲","artist":"Crowd Lu","streams":"47847","url":"https://open.spotify.com/track/3OC84eKMxRJ4x0Hcwl9i4i"},{"number":"2","trackName":"飞鸟和蝉","artist":"Ren Ran","streams":"39182","url":"https://open.spotify.com/track/3IveWAHTMxZA4KYBPnylq5"},{"number":"3","trackName":"在這座城市遺失了你","artist":"告五人","streams":"36794","url":"https://open.spotify.com/track/1Ytgo9ipdlTsf6wlg6sXf3"},{"number":"4","trackName":"想見你想見你想見你(電視劇\"想見你\"片尾曲)","artist":"831","streams":"35574","url":"https://open.spotify.com/track/69zgyr5HVKdInjeKpq1qHa"},{"number":"5","trackName":"Celebrity","artist":"IU","streams":"32579","url":"https://open.spotify.com/track/4RewTiGEGoO7FWNZUmp1f4"},{"number":"6","trackName":"怎麼了","artist":"Eric Chou","streams":"28720","url":"https://open.spotify.com/track/5cU1O9P0EDA0rPkPDykhIm"},{"number":"7","trackName":"drivers license","artist":"Olivia Rodrigo","streams":"26991","url":"https://open.spotify.com/track/7lPN2DXiMsVn7XUKtOW1CS"},{"number":"8","trackName":"嚣张","artist":"En","streams":"23766","url":"https://open.spotify.com/track/3t8M86tiO0aKMMTXzRrFn8"},{"number":"9","trackName":"天黑請閉眼 (feat. 邱鋒澤)","artist":"Nine Chen","streams":"22535","url":"https://open.spotify.com/track/0bIbgooxvBkww2ZGeu8VMR"},{"number":"10","trackName":"Dynamite","artist":"BTS","streams":"22140","url":"https://open.spotify.com/track/4saklk6nie3yiGePpBwUoc"}],"UA":[{"number":"1","trackName":"Моя голова винтом","artist":"kostromin","streams":"13431","url":"https://open.spotify.com/track/4KrhaZm4JRkNO4HRdLvJIG"},{"number":"2","trackName":"Astronaut In The Ocean","artist":"Masked Wolf","streams":"12071","url":"https://open.spotify.com/track/3VT8hOC5vuDXBsHrR53WFh"},{"number":"3","trackName":"Cristal & МОЁТ","artist":"MORGENSHTERN","streams":"11097","url":"https://open.spotify.com/track/4KfmruShP5zOi9hYjM76e6"},{"number":"4","trackName":"The Business","artist":"Tiësto","streams":"9022","url":"https://open.spotify.com/track/6f3Slt0GbA2bPZlz0aIFXN"},{"number":"5","trackName":"Снова я напиваюсь","artist":"SLAVA MARLOW","streams":"8399","url":"https://open.spotify.com/track/18t2lAzaHW2bJomYeyzrpy"},{"number":"6","trackName":"Camry 3.5","artist":"UncleFlexxx","streams":"8209","url":"https://open.spotify.com/track/4qTNag73xHeQLFF5fEJWUQ"},{"number":"7","trackName":"Чистый - OST «Псих»","artist":"Scriptonite","streams":"8148","url":"https://open.spotify.com/track/2Z0OcpA4i1KayJbXn800le"},{"number":"8","trackName":"Дежавю","artist":"kizaru","streams":"7807","url":"https://open.spotify.com/track/1GOiMxQXZUzjzH0Sxpck0B"},{"number":"9","trackName":"Голодный пёс [prod. by Pretty Scream]","artist":"SEEMEE","streams":"7580","url":"https://open.spotify.com/track/4KiFqaxjnmVm0gyIPIRRgH"},{"number":"10","trackName":"Blinding Lights","artist":"The Weeknd","streams":"7446","url":"https://open.spotify.com/track/0VjIjW4GlUZAMYd2vXMi3b"}],"UY":[{"number":"1","trackName":"Bandido","artist":"Myke Towers","streams":"22579","url":"https://open.spotify.com/track/1xK1Gg9SxG8fy2Ya373oqb"},{"number":"2","trackName":"Hecha Pa' Mi","artist":"Boza","streams":"17930","url":"https://open.spotify.com/track/3VvA1wSxukMLsvXoXtlwWx"},{"number":"3","trackName":"BICHOTA","artist":"KAROL G","streams":"17214","url":"https://open.spotify.com/track/7vrJn5hDSXRmdXoR30KgF1"},{"number":"4","trackName":"DÁKITI","artist":"Bad Bunny","streams":"16361","url":"https://open.spotify.com/track/4MzXwWMhyBbmu6hOcLVD49"},{"number":"5","trackName":"LA NOCHE DE ANOCHE","artist":"Bad Bunny","streams":"15950","url":"https://open.spotify.com/track/2XIc1pqjXV3Cr2BQUGNBck"},{"number":"6","trackName":"Si Me Tomo Una Cerveza","artist":"Migrantes","streams":"15284","url":"https://open.spotify.com/track/3lCbsHaN1wCxyDzcNN2x4N"},{"number":"7","trackName":"Baila Conmigo (with Rauw Alejandro)","artist":"Selena Gomez","streams":"14420","url":"https://open.spotify.com/track/0D75ciM842cdUMKSMfAR9y"},{"number":"8","trackName":"L-Gante Rkt","artist":"Papu DJ","streams":"14007","url":"https://open.spotify.com/track/6EHrppRT1Uj4cyShAujxFu"},{"number":"9","trackName":"Ella No Es Tuya - Remix","artist":"Rochy RD","streams":"13835","url":"https://open.spotify.com/track/5YYW3yRktprLRr47WK219Y"},{"number":"10","trackName":"La Nota","artist":"Manuel Turizo","streams":"13401","url":"https://open.spotify.com/track/7ndTONDDRFGiPnnhOzOXxq"}],"VN":[{"number":"1","trackName":"Chúng Ta Của Hiện Tại","artist":"Sơn Tùng M-TP","streams":"43645","url":"https://open.spotify.com/track/17iGUekw5nFt5mIRJcUm3R"},{"number":"2","trackName":"Tình Bạn Diệu Kỳ","artist":"AMEE","streams":"37564","url":"https://open.spotify.com/track/2f8Ew6sB7KHlTiH9NTLvVM"},{"number":"3","trackName":"Nàng Thơ","artist":"Hoang Dung","streams":"34404","url":"https://open.spotify.com/track/6rVaOdWvFaNyVVXda0NPJy"},{"number":"4","trackName":"Đi Về Nhà","artist":"Đen","streams":"25062","url":"https://open.spotify.com/track/7LVrrX8pkzI9fMF88nGabt"},{"number":"5","trackName":"Bước Qua Mùa Cô Đơn","artist":"Vũ.","streams":"24971","url":"https://open.spotify.com/track/7wkX67ruxr3x2GFz6vyIX9"},{"number":"6","trackName":"Gác Lại Âu Lo","artist":"Da LAB","streams":"21662","url":"https://open.spotify.com/track/6HpDKKSDZ8QpSHfikENIBC"},{"number":"7","trackName":"Trên Tình Bạn Dưới Tình Yêu","artist":"MIN","streams":"20629","url":"https://open.spotify.com/track/5zH2inEP6THOY8tomr3DdZ"},{"number":"8","trackName":"Chuyện Rằng","artist":"Thịnh Suy","streams":"20583","url":"https://open.spotify.com/track/3VOeGtJwJh2jslvQAFaaEn"},{"number":"9","trackName":"At My Worst","artist":"Pink Sweat$","streams":"20424","url":"https://open.spotify.com/track/2MJz8BxxMsERULatmBikDH"},{"number":"10","trackName":"từ thích thích thành thương thương","artist":"AMEE","streams":"19064","url":"https://open.spotify.com/track/1fh5Sf3fFESFOS8D82RQiI"}],"ZA":[{"number":"1","trackName":"drivers license","artist":"Olivia Rodrigo","streams":"13244","url":"https://open.spotify.com/track/7lPN2DXiMsVn7XUKtOW1CS"},{"number":"2","trackName":"Calling My Phone","artist":"Lil Tjay","streams":"11565","url":"https://open.spotify.com/track/5Kskr9LcNYa0tpt5f0ZEJx"},{"number":"3","trackName":"The Business","artist":"Tiësto","streams":"10651","url":"https://open.spotify.com/track/6f3Slt0GbA2bPZlz0aIFXN"},{"number":"4","trackName":"Save Your Tears","artist":"The Weeknd","streams":"9439","url":"https://open.spotify.com/track/5QO79kh1waicV47BqGRL3g"},{"number":"5","trackName":"Blinding Lights","artist":"The Weeknd","streams":"9270","url":"https://open.spotify.com/track/0VjIjW4GlUZAMYd2vXMi3b"},{"number":"6","trackName":"Streets","artist":"Doja Cat","streams":"8524","url":"https://open.spotify.com/track/60ynsPSSKe6O3sfwRnIBRf"},{"number":"7","trackName":"Mood (feat. iann dior)","artist":"24kGoldn","streams":"8024","url":"https://open.spotify.com/track/3tjFYV6RSFtuktYl3ZtYcq"},{"number":"8","trackName":"Umsebenzi Wethu","artist":"Busta 929","streams":"7637","url":"https://open.spotify.com/track/2H1hYPeKgIQAp439cx7GsX"},{"number":"9","trackName":"Head & Heart (feat. MNEK)","artist":"Joel Corry","streams":"7468","url":"https://open.spotify.com/track/6cx06DFPPHchuUAcTxznu9"},{"number":"10","trackName":"Up","artist":"Cardi B","streams":"7306","url":"https://open.spotify.com/track/1M4OcYkxAtu3ErzSgDEfoi"}]}