{"US":["3aQem4jVGdhtg116TmJnHz","7MAibcTli4IisCtbHKrGMh","65OVbaJR5O1RmwOQx0875b","6tDDoYIxWvMLTdKpjFkc1B","7lPN2DXiMsVn7XUKtOW1CS","1M4OcYkxAtu3ErzSgDEfoi","5Kskr9LcNYa0tpt5f0ZEJx","60ynsPSSKe6O3sfwRnIBRf","3YJJjQPAbDT7mGpX3WtQ9A","5QO79kh1waicV47BqGRL3g"],"GB":["7lPN2DXiMsVn7XUKtOW1CS","5J5CpT6bgE6KYKk23jgp9W","5Kskr9LcNYa0tpt5f0ZEJx","7pnQ23WgZca9jEfMts9qsR","27OeeYzk6klgBh83TSvGMA","6f3Slt0GbA2bPZlz0aIFXN","4I5bvu2KDsrCg0EWHIcvul","0UCKUJU94sx8XBQnaNsRkB","4cG7HUWYHBV6R6tHn1gxrl","3iw6V4LH7yPj1ESORX9RIN"],"AR":["1Crj1zkRMpsEjb9NOR6Zof","7I8L3vYCLThw2FDrE6LuzE","5YYW3yRktprLRr47WK219Y","1xK1Gg9SxG8fy2Ya373oqb","6EHrppRT1Uj4cyShAujxFu","3OXxCquI8i14EigwILaLx9","2XIc1pqjXV3Cr2BQUGNBck","4fipVdNyG6zx7nxuqHScsy","7vrJn5hDSXRmdXoR30KgF1","3VvA1wSxukMLsvXoXtlwWx"],"AT":["3iw6V4LH7yPj1ESORX9RIN","3VT8hOC5vuDXBsHrR53WFh","7lPN2DXiMsVn7XUKtOW1CS","27OeeYzk6klgBh83TSvGMA","4hSJUp6k7QeHLxU32MrLIU","6a3kNt1UlUOapDKmEr3JzZ","5QO79kh1waicV47BqGRL3g","6f3Slt0GbA2bPZlz0aIFXN","4DnHEa1fuf3bn61AwT8Qiv","3tjFYV6RSFtuktYl3ZtYcq"],"AU":["02MWAaffLxlfxAUY7c5dvx","7lPN2DXiMsVn7XUKtOW1CS","27OeeYzk6klgBh83TSvGMA","5Kskr9LcNYa0tpt5f0ZEJx","3VT8hOC5vuDXBsHrR53WFh","6f3Slt0GbA2bPZlz0aIFXN","7MAibcTli4IisCtbHKrGMh","5QO79kh1waicV47BqGRL3g","5uEYRdEIh9Bo4fpjDd4Na9","3FAJ6O0NOHQV8Mc5Ri6ENp"],"BE":["7lPN2DXiMsVn7XUKtOW1CS","6f3Slt0GbA2bPZlz0aIFXN","4cG7HUWYHBV6R6tHn1gxrl","27OeeYzk6klgBh83TSvGMA","3iw6V4LH7yPj1ESORX9RIN","5QO79kh1waicV47BqGRL3g","3VT8hOC5vuDXBsHrR53WFh","3F1P0QzdXtBz0MXy7KIO5w","3tjFYV6RSFtuktYl3ZtYcq","6ft4hAq6yde8jPZY2i5zLr"],"BG":["3VT8hOC5vuDXBsHrR53WFh","589KeND3ebjbfhs5GfGGyx","6Fz0IEZ0qHeu3cEbRDqSnU","60ynsPSSKe6O3sfwRnIBRf","1M4OcYkxAtu3ErzSgDEfoi","6f3Slt0GbA2bPZlz0aIFXN","1t9WgS8FN0534tLBRwbaxO","2MUIxQQ7YVvefJ17ZVFSId","6W2jsJG6MPPJ6xTWcNEeHr","7hxHWCCAIIxFLCzvDgnQHX"],"BO":["1xK1Gg9SxG8fy2Ya373oqb","4MzXwWMhyBbmu6hOcLVD49","2XIc1pqjXV3Cr2BQUGNBck","6tDDoYIxWvMLTdKpjFkc1B","7vrJn5hDSXRmdXoR30KgF1","5YYW3yRktprLRr47WK219Y","3VvA1wSxukMLsvXoXtlwWx","079Ey5uxL04AKPQgVQwx5h","4loQgPwJHocL3dFwLfjb1J","7Bk0uXKk1uPT0XuQbpFzvs"],"BR":["2MZQAvsA7aZDssppBLRxYp","58pgi1RpcU2fVJsxhm7BIr","1ere9b9vDw2N3m9d4uiXxa","7EWXP47VlXKO3r7mNxuWHw","27X3qzgB0Show6qfw5wNOK","2nZj5YymF54qhAu7RneVP6","07AQkmp456NpEnT8HR7WLy","5m5aY6S9ttfIG157xli2Rs","7GLWWrk1YlkPYqJK3ynIA0","6sPBi0qLI6KM3yXX56NxsA"],"CA":["3aQem4jVGdhtg116TmJnHz","65OVbaJR5O1RmwOQx0875b","5Kskr9LcNYa0tpt5f0ZEJx","3VT8hOC5vuDXBsHrR53WFh","7lPN2DXiMsVn7XUKtOW1CS","7MAibcTli4IisCtbHKrGMh","5QO79kh1waicV47BqGRL3g","1M4OcYkxAtu3ErzSgDEfoi","4u4NyuceXP7Uzh7XFJKCr1","5nujrmhLynf4yMoMtj8AQF"],"CH":["3VT8hOC5vuDXBsHrR53WFh","3iw6V4LH7yPj1ESORX9RIN","5QO79kh1waicV47BqGRL3g","7lPN2DXiMsVn7XUKtOW1CS","6f3Slt0GbA2bPZlz0aIFXN","54OBgO0Xwu20Jak9TMXbR7","27OeeYzk6klgBh83TSvGMA","5SFXOMJJ334Wn2PwBHeRZN","4cG7HUWYHBV6R6tHn1gxrl","5YaskwnGDZFDRipaqzbwQx"],"CL":["7Bk0uXKk1uPT0XuQbpFzvs","1xK1Gg9SxG8fy2Ya373oqb","4MzXwWMhyBbmu6hOcLVD49","5YYW3yRktprLRr47WK219Y","2XIc1pqjXV3Cr2BQUGNBck","2TksvaRivgAEj780DgRB73","3VvA1wSxukMLsvXoXtlwWx","7vrJn5hDSXRmdXoR30KgF1","2mM3gZ0BbPwPPMelbA8vgt","1Ymx1Q7EXkxd7FwKypAQ6o"],"CO":["1xK1Gg9SxG8fy2Ya373oqb","4MzXwWMhyBbmu6hOcLVD49","6tDDoYIxWvMLTdKpjFkc1B","2XIc1pqjXV3Cr2BQUGNBck","7vrJn5hDSXRmdXoR30KgF1","5YYW3yRktprLRr47WK219Y","6RV9pRLIQiXm3qTGeyQluf","5xwjEzvJ2OSdnHlzusKNYA","7Bk0uXKk1uPT0XuQbpFzvs","4loQgPwJHocL3dFwLfjb1J"],"CR":["1xK1Gg9SxG8fy2Ya373oqb","4MzXwWMhyBbmu6hOcLVD49","6tDDoYIxWvMLTdKpjFkc1B","5YYW3yRktprLRr47WK219Y","2XIc1pqjXV3Cr2BQUGNBck","3VvA1wSxukMLsvXoXtlwWx","7vrJn5hDSXRmdXoR30KgF1","2TksvaRivgAEj780DgRB73","4loQgPwJHocL3dFwLfjb1J","2mM3gZ0BbPwPPMelbA8vgt"],"CZ":["3VT8hOC5vuDXBsHrR53WFh","6f3Slt0GbA2bPZlz0aIFXN","0aJwgjOHTpyw0hw4nXl3Xd","7lPN2DXiMsVn7XUKtOW1CS","3tjFYV6RSFtuktYl3ZtYcq","65sTVVVMDnczku5Gt2PTmt","35nvMkQglkoeydD81a0b77","0VjIjW4GlUZAMYd2vXMi3b","5QO79kh1waicV47BqGRL3g","6ft4hAq6yde8jPZY2i5zLr"],"DE":["6a3kNt1UlUOapDKmEr3JzZ","3iw6V4LH7yPj1ESORX9RIN","3VT8hOC5vuDXBsHrR53WFh","4hSJUp6k7QeHLxU32MrLIU","6V1lWr7s8CO5VkxXe4hBtg","4cG7HUWYHBV6R6tHn1gxrl","6f3Slt0GbA2bPZlz0aIFXN","0tcWtn95oGyM1OElWWos4q","4DnHEa1fuf3bn61AwT8Qiv","5YaskwnGDZFDRipaqzbwQx"],"DK":["696pTNllVLM7EK9wMIuYdJ","29s2dhQ00vpr6eTI00Kc77","7lPN2DXiMsVn7XUKtOW1CS","5QO79kh1waicV47BqGRL3g","4u4NyuceXP7Uzh7XFJKCr1","27OeeYzk6klgBh83TSvGMA","4vAReYtMpAAFK6cyTE8WkZ","6f3Slt0GbA2bPZlz0aIFXN","5KLDajsSLvA5n2zTwKycvF","6WELXrF1hsdUZEcasR1DGG"],"DO":["1xK1Gg9SxG8fy2Ya373oqb","2XIc1pqjXV3Cr2BQUGNBck","4MzXwWMhyBbmu6hOcLVD49","6wQufshN8RwGazPyDQ0WXM","7Bk0uXKk1uPT0XuQbpFzvs","5YYW3yRktprLRr47WK219Y","6tDDoYIxWvMLTdKpjFkc1B","2TksvaRivgAEj780DgRB73","6qraVL4IJaIj0IuEexYJNa","4loQgPwJHocL3dFwLfjb1J"],"EC":["4MzXwWMhyBbmu6hOcLVD49","1xK1Gg9SxG8fy2Ya373oqb","2XIc1pqjXV3Cr2BQUGNBck","6tDDoYIxWvMLTdKpjFkc1B","7vrJn5hDSXRmdXoR30KgF1","5YYW3yRktprLRr47WK219Y","7Bk0uXKk1uPT0XuQbpFzvs","2TksvaRivgAEj780DgRB73","3VvA1wSxukMLsvXoXtlwWx","4loQgPwJHocL3dFwLfjb1J"],"EE":["3VT8hOC5vuDXBsHrR53WFh","1Ae5AcTlKsTEpksomr4oDK","5QO79kh1waicV47BqGRL3g","7lPN2DXiMsVn7XUKtOW1CS","60ynsPSSKe6O3sfwRnIBRf","7IoTZnck9r11NCj5M0QG81","06HOLlh8Sh5jHptg37zMSz","3iw6V4LH7yPj1ESORX9RIN","4cG7HUWYHBV6R6tHn1gxrl","6f3Slt0GbA2bPZlz0aIFXN"],"ES":["2TksvaRivgAEj780DgRB73","5YYW3yRktprLRr47WK219Y","1xK1Gg9SxG8fy2Ya373oqb","0VWLId2RwPCno9s1cJm2Vy","3SK45LddxlEkzI8OWO9Eyo","7Bk0uXKk1uPT0XuQbpFzvs","2mM3gZ0BbPwPPMelbA8vgt","5ddFjrPG8NgQQ6xlOQIVd2","73O30uMI7n6DuzBmbtO7kC","1wPAOYQJcGSqvXkqcQHExr"],"FI":["6nU4btGccMwMywAAl6cNSD","3qw9rbM22j7TauihIva5Js","6A8B1kJ9ZNHbl2uFPN6Wtm","3VT8hOC5vuDXBsHrR53WFh","2SREBxoqvxhB0wQHgLeNVI","3iw6V4LH7yPj1ESORX9RIN","4sFDPk9PwpHWDcXN8rY2oA","26tRJottEBj78dqKREPeBT","5QO79kh1waicV47BqGRL3g","3bKFbtcIr4tq1obGrUJ0dp"],"FR":["2m7Bcs4ZJcwhZB9l75sem5","5LYRIyhmlrDAQsYdHEvP0f","360oH1CqXe9XXzbbi6hvyr","1SelxYHPb04GjUy0oYV1Jw","2vBET2pmrQqafaS6zIaYta","4CWcaGtaOyAqBDKIeZMUe0","4uOiz6kmw0NkJLWAS0etWx","3F1P0QzdXtBz0MXy7KIO5w","4MzXwWMhyBbmu6hOcLVD49","7CAZp2oaUNJ47vtAZDfKn6"],"GR":["6zFIf7W0pKa9HO50dw5E8u","5tdAToNfTBrzl0CouCqepZ","5g5GOBG3mTODUxegwjK4VL","6tGl1mj5CyoB1hUtOKyhkQ","3VT8hOC5vuDXBsHrR53WFh","7eZxh83S9spEfb3gAIcZZW","54EXZcuRYIFW75Y5Bxenxt","7sqV5wrcZH0B4q8X9uHKFJ","0Az2D1ByNU09je0ZtzDcHm","6m9mAgw4rMkGUkHuSAFdDB"],"GT":["4MzXwWMhyBbmu6hOcLVD49","1xK1Gg9SxG8fy2Ya373oqb","2XIc1pqjXV3Cr2BQUGNBck","7vrJn5hDSXRmdXoR30KgF1","6tDDoYIxWvMLTdKpjFkc1B","4loQgPwJHocL3dFwLfjb1J","3VvA1wSxukMLsvXoXtlwWx","1yoMvmasuxZfqHEipJhRbp","7Bk0uXKk1uPT0XuQbpFzvs","5RubKOuDoPn5Kj5TLVxSxY"],"HK":["2pn8dNVSpYnAtlKFC8Q0DJ","2dHoVW9AxJVSRebPRyV2aA","7MAibcTli4IisCtbHKrGMh","32QnXosZq7A11knnBAEqk7","06sDxr7MbbwFyTP1f6rvvl","63QmxPL3QlchvXcHLsI6UM","4xL01OuFjqizPDclF8gDpl","4ckh5VN2HYQ8TzS51Nh7ol","4IkQXb1IdIziAJmO3FODo7","3OC84eKMxRJ4x0Hcwl9i4i"],"HN":["4MzXwWMhyBbmu6hOcLVD49","2XIc1pqjXV3Cr2BQUGNBck","1xK1Gg9SxG8fy2Ya373oqb","6tDDoYIxWvMLTdKpjFkc1B","7Bk0uXKk1uPT0XuQbpFzvs","7vrJn5hDSXRmdXoR30KgF1","5RubKOuDoPn5Kj5TLVxSxY","5YYW3yRktprLRr47WK219Y","4loQgPwJHocL3dFwLfjb1J","3VvA1wSxukMLsvXoXtlwWx"],"HU":["3VT8hOC5vuDXBsHrR53WFh","6f3Slt0GbA2bPZlz0aIFXN","6i7zAdNhzUN2k1HcrBxPHG","6cx06DFPPHchuUAcTxznu9","3tjFYV6RSFtuktYl3ZtYcq","6ft4hAq6yde8jPZY2i5zLr","78Jj0xPR2y4KMAtYuWpRly","5QO79kh1waicV47BqGRL3g","7lPN2DXiMsVn7XUKtOW1CS","5YaskwnGDZFDRipaqzbwQx"],"ID":["3pCt2wRdBDa2kCisIdHWgF","2pn8dNVSpYnAtlKFC8Q0DJ","3FAJ6O0NOHQV8Mc5Ri6ENp","4kfjA6WfgKBt7I7YKuDCkU","630DpnzdfjdVqv2yLfPbAX","2dHoVW9AxJVSRebPRyV2aA","2MJz8BxxMsERULatmBikDH","0ZEYRVISCaqz5yamWZWzaA","7MAibcTli4IisCtbHKrGMh","7lPN2DXiMsVn7XUKtOW1CS"],"IE":["7lPN2DXiMsVn7XUKtOW1CS","6f3Slt0GbA2bPZlz0aIFXN","0siYMEsGrzzzlWLXK5zJfS","4cG7HUWYHBV6R6tHn1gxrl","27OeeYzk6klgBh83TSvGMA","5QO79kh1waicV47BqGRL3g","02MWAaffLxlfxAUY7c5dvx","6ft4hAq6yde8jPZY2i5zLr","3iw6V4LH7yPj1ESORX9RIN","5YaskwnGDZFDRipaqzbwQx"],"IL":["2qmJ2h1UdncRMPI2DMRWvK","7kJ3RSCzrosxxkNgJtQ53v","7v63pRo1RXcYzrCxaMkGc5","3VT8hOC5vuDXBsHrR53WFh","4L4dPjtEVEpZ0ER2deHAJA","74pfNNxGlwSyokwtqxHcDa","4qAHhdpiGcbzqwjqmwuXwj","3ygLMqx3CNVJmQAnriDDh2","5QO79kh1waicV47BqGRL3g","66iaD8MCoVnBtqUhuzdglT"],"IN":["2ufLEVbzvEcJ3subW8jBUp","58f4twRnbZOOVUhMUpplJ4","1baHxgYktT8eDdmtTozJF9","2PEo8JQ48mfEv8a2HLqDvt","3VT8hOC5vuDXBsHrR53WFh","1smFN2CLqGROu0J0UyvDfL","5mnvugwfFYnJm9zuyGkgqF","2FCXQHugkoHE1K3tiDu8pu","39QJ7KkN3L8LLqQqsO85W1","2MJz8BxxMsERULatmBikDH"],"IS":["4O0LQKVT6hGmVGNwizmydg","7mGZklollA25HGdPh3jWeW","5VrbuzqAjCAFSa7MpGRXWI","5qI0p2E7BxBxYRJknYr6Gg","5wGoaKvq8Vlst7ZqKyQbvn","5QO79kh1waicV47BqGRL3g","7lPN2DXiMsVn7XUKtOW1CS","04ZMCgKlsRcTDrxGMKCrAx","6f3Slt0GbA2bPZlz0aIFXN","3iw6V4LH7yPj1ESORX9RIN"],"IT":["5vYXOk1umkpp7JhXZm6rDI","1eIS75JS5rfbJpSu6ZC9EO","1lWWoec2z1j88GRblI5anV","0ZqHo6eTBHUcOVjZzPvftT","0HyDNYQmQ3obfA81D3y9tG","1uXJYnCsXy2v50y0fDEEiV","5qn15Hs4s26YaNd5UWVe00","00QN58Gx571pB1MEuBAcmL","3RqausOoS1TMLly9Q12JgT","4jmvkbDw0cuWD2Fi9VswFQ"],"JP":["7dH0dpi751EoguDDg3xx6J","4saklk6nie3yiGePpBwUoc","6MCjmGYlw6mQVWRFVgBRvB","0XZyF9lv6diMt4bxThOL0h","06XQvnJb53SUYmlWIhUXUi","5RhWszHMSKzb7KiXk4Ae0M","1zd35Y44Blc1CwwVbW3Qnk","6EzZn96uOc9JsVGNRpx06n","0cSkn2l67csUljEy0EEBPn","7AIj86wFWqm7X1TZ2hzHwS"],"LT":["5QO79kh1waicV47BqGRL3g","3VT8hOC5vuDXBsHrR53WFh","60ynsPSSKe6O3sfwRnIBRf","6tDDoYIxWvMLTdKpjFkc1B","7lPN2DXiMsVn7XUKtOW1CS","6f3Slt0GbA2bPZlz0aIFXN","5YaskwnGDZFDRipaqzbwQx","4cG7HUWYHBV6R6tHn1gxrl","0VjIjW4GlUZAMYd2vXMi3b","7MAibcTli4IisCtbHKrGMh"],"LU":["7lPN2DXiMsVn7XUKtOW1CS","3VT8hOC5vuDXBsHrR53WFh","5QO79kh1waicV47BqGRL3g","6f3Slt0GbA2bPZlz0aIFXN","5Kskr9LcNYa0tpt5f0ZEJx","3aQem4jVGdhtg116TmJnHz","360oH1CqXe9XXzbbi6hvyr","3tjFYV6RSFtuktYl3ZtYcq","27OeeYzk6klgBh83TSvGMA","4cG7HUWYHBV6R6tHn1gxrl"],"LV":["3VT8hOC5vuDXBsHrR53WFh","5QO79kh1waicV47BqGRL3g","60ynsPSSKe6O3sfwRnIBRf","7lPN2DXiMsVn7XUKtOW1CS","6f3Slt0GbA2bPZlz0aIFXN","12Kknh5NqqAukiyevjDQkT","4cG7HUWYHBV6R6tHn1gxrl","6tDDoYIxWvMLTdKpjFkc1B","2h9pSMHx48Q4SOWsvEiah5","2QjOHCTQ1Jl3zawyYOpxh6"],"MX":["6tDDoYIxWvMLTdKpjFkc1B","4MzXwWMhyBbmu6hOcLVD49","7vrJn5hDSXRmdXoR30KgF1","1xK1Gg9SxG8fy2Ya373oqb","2XIc1pqjXV3Cr2BQUGNBck","5QO79kh1waicV47BqGRL3g","1yoMvmasuxZfqHEipJhRbp","079Ey5uxL04AKPQgVQwx5h","4loQgPwJHocL3dFwLfjb1J","5YYW3yRktprLRr47WK219Y"],"MY":["2pn8dNVSpYnAtlKFC8Q0DJ","2dHoVW9AxJVSRebPRyV2aA","3FAJ6O0NOHQV8Mc5Ri6ENp","7MAibcTli4IisCtbHKrGMh","7lPN2DXiMsVn7XUKtOW1CS","2MJz8BxxMsERULatmBikDH","4u4NyuceXP7Uzh7XFJKCr1","5QO79kh1waicV47BqGRL3g","7F1CiKqrY44kh5cDqwHOnx","1J14CdDAvBTE1AJYUOwl6C"],"NI":["4MzXwWMhyBbmu6hOcLVD49","2XIc1pqjXV3Cr2BQUGNBck","1xK1Gg9SxG8fy2Ya373oqb","6tDDoYIxWvMLTdKpjFkc1B","5YYW3yRktprLRr47WK219Y","7vrJn5hDSXRmdXoR30KgF1","3VvA1wSxukMLsvXoXtlwWx","26w9NTiE9NGjW1ZvIOd1So","5RubKOuDoPn5Kj5TLVxSxY","4loQgPwJHocL3dFwLfjb1J"],"NL":["0Fl4PBfIwC5G1IQAF1luUm","7BRKEcW05hOZMJ3bKOOzQl","3iw6V4LH7yPj1ESORX9RIN","3aViSiRTiK1e5OqJtUk3MS","4cG7HUWYHBV6R6tHn1gxrl","7lPN2DXiMsVn7XUKtOW1CS","27OeeYzk6klgBh83TSvGMA","1CwhKXOiL4vyUcNYqo3dVF","7kqftRMUoBeeyb4ZkAKPiA","3yraHvsUkmnJjGhOrx1CSg"],"NO":["3iw6V4LH7yPj1ESORX9RIN","1oKXshzJtz3zDA6dJY8VlZ","04k0QThdHEp7kg3FpXVh0Q","72gCZzPrTYIwfpztcL64rP","7lPN2DXiMsVn7XUKtOW1CS","5QO79kh1waicV47BqGRL3g","2Y7npn076wSZJgH8HVr2B2","27OeeYzk6klgBh83TSvGMA","4u4NyuceXP7Uzh7XFJKCr1","2bSVFkcYAQwkGlGK7v1Ihl"],"NZ":["7MAibcTli4IisCtbHKrGMh","3FAJ6O0NOHQV8Mc5Ri6ENp","7lPN2DXiMsVn7XUKtOW1CS","2yI8xyHgyhCXyw0Vq98twb","02MWAaffLxlfxAUY7c5dvx","5Kskr9LcNYa0tpt5f0ZEJx","3YJJjQPAbDT7mGpX3WtQ9A","2Tf3a4gkBbrN2UbMNbwtdQ","3TaGtHDHWQ7TfPpX0eJrtB","27OeeYzk6klgBh83TSvGMA"],"PA":["1xK1Gg9SxG8fy2Ya373oqb","4MzXwWMhyBbmu6hOcLVD49","5YYW3yRktprLRr47WK219Y","2XIc1pqjXV3Cr2BQUGNBck","3VvA1wSxukMLsvXoXtlwWx","2TksvaRivgAEj780DgRB73","6tDDoYIxWvMLTdKpjFkc1B","7Bk0uXKk1uPT0XuQbpFzvs","7vrJn5hDSXRmdXoR30KgF1","4f2nbpKWfnj7tNyL2Ihj9n"],"PE":["1xK1Gg9SxG8fy2Ya373oqb","5YYW3yRktprLRr47WK219Y","2XIc1pqjXV3Cr2BQUGNBck","6tDDoYIxWvMLTdKpjFkc1B","4MzXwWMhyBbmu6hOcLVD49","3VvA1wSxukMLsvXoXtlwWx","4loQgPwJHocL3dFwLfjb1J","2mM3gZ0BbPwPPMelbA8vgt","7vrJn5hDSXRmdXoR30KgF1","6RV9pRLIQiXm3qTGeyQluf"],"PH":["3FAJ6O0NOHQV8Mc5Ri6ENp","2pn8dNVSpYnAtlKFC8Q0DJ","7MAibcTli4IisCtbHKrGMh","7lPN2DXiMsVn7XUKtOW1CS","2MJz8BxxMsERULatmBikDH","1NUw61RX4Wtmxw7CLiP4kP","2dHoVW9AxJVSRebPRyV2aA","7F1CiKqrY44kh5cDqwHOnx","7bUvgvAf0tdQIty95lV5wf","4saklk6nie3yiGePpBwUoc"],"PL":["1ViGe38tmbdDapmz5ReZQR","7fuvhZxxLou4qRRo4Z63wE","7umEhzfURpGTSRbcX84qLy","27gknDBOqYJmOFYyaOBAfa","7HvMlXXpPKj3nYClkyoxbE","7lPN2DXiMsVn7XUKtOW1CS","4XZxxP6ilbl56BooNjq7Ki","5QO79kh1waicV47BqGRL3g","1k66TKeE51BtgF0q2ZOCOy","4yP4P2pHqtejjQ1l12J8bA"],"PT":["27OeeYzk6klgBh83TSvGMA","7lPN2DXiMsVn7XUKtOW1CS","7MAibcTli4IisCtbHKrGMh","1h1JMmAzXR6lWJ7KnJQkU7","07AQkmp456NpEnT8HR7WLy","4MzXwWMhyBbmu6hOcLVD49","3VT8hOC5vuDXBsHrR53WFh","6f3Slt0GbA2bPZlz0aIFXN","0QglpM23kl9ldvVdoYNZwF","5QO79kh1waicV47BqGRL3g"],"PY":["1xK1Gg9SxG8fy2Ya373oqb","2XIc1pqjXV3Cr2BQUGNBck","5YYW3yRktprLRr47WK219Y","4MzXwWMhyBbmu6hOcLVD49","4PEfJZpVjdclfzZ9XO8uDw","7I8L3vYCLThw2FDrE6LuzE","3VvA1wSxukMLsvXoXtlwWx","27X3qzgB0Show6qfw5wNOK","7vrJn5hDSXRmdXoR30KgF1","4loQgPwJHocL3dFwLfjb1J"],"RO":["3VT8hOC5vuDXBsHrR53WFh","6tDDoYIxWvMLTdKpjFkc1B","6f3Slt0GbA2bPZlz0aIFXN","60ynsPSSKe6O3sfwRnIBRf","5QO79kh1waicV47BqGRL3g","7lPN2DXiMsVn7XUKtOW1CS","0VjIjW4GlUZAMYd2vXMi3b","1M4OcYkxAtu3ErzSgDEfoi","1t9WgS8FN0534tLBRwbaxO","5Kskr9LcNYa0tpt5f0ZEJx"],"RU":["12Kknh5NqqAukiyevjDQkT","4KiFqaxjnmVm0gyIPIRRgH","1ngGGsWzGONyiOlxdXRDr7","3VT8hOC5vuDXBsHrR53WFh","2bqS0QtnXGjOYs3z6VtSyW","6PAPPKv7XPCqPEG95UaOFa","3HHVtWGKwhMwjUfsQGztzt","4KfmruShP5zOi9hYjM76e6","3LRmMWVGsf9mprzLlFLJXR","2Z0OcpA4i1KayJbXn800le"],"SE":["5zxZ7M4RgWZUHlMEwac8vt","4tGPi30jgutml0z5QgNd8Q","4dxeRrYgeAQ1F0uH9g04lN","61YmcO62hGjw1RlDHZ0XEg","7t3VznmzfrDXFyexb2wA0q","6inhRGv7e8iqDEMRQuFk0W","41iZhFesLQ6JLjyPxI4LLL","09ZI6ytqLZe1sRXLKPKZNe","3MMJuk00QLVAjS6vwBZ67V","5nBi3tQiXWt70G6UlXB86E"],"SG":["2pn8dNVSpYnAtlKFC8Q0DJ","2dHoVW9AxJVSRebPRyV2aA","7MAibcTli4IisCtbHKrGMh","3FAJ6O0NOHQV8Mc5Ri6ENp","7lPN2DXiMsVn7XUKtOW1CS","2MJz8BxxMsERULatmBikDH","5QO79kh1waicV47BqGRL3g","4u4NyuceXP7Uzh7XFJKCr1","1J14CdDAvBTE1AJYUOwl6C","3VT8hOC5vuDXBsHrR53WFh"],"SK":["3VT8hOC5vuDXBsHrR53WFh","0N9Fccu5ESGwWPJ3MU9Yt5","6f3Slt0GbA2bPZlz0aIFXN","7lPN2DXiMsVn7XUKtOW1CS","5QO79kh1waicV47BqGRL3g","6ft4hAq6yde8jPZY2i5zLr","3tjFYV6RSFtuktYl3ZtYcq","1iAyJBksvAI6DQEnzv8l1E","6cx06DFPPHchuUAcTxznu9","4u4NyuceXP7Uzh7XFJKCr1"],"SV":["4MzXwWMhyBbmu6hOcLVD49","1xK1Gg9SxG8fy2Ya373oqb","2XIc1pqjXV3Cr2BQUGNBck","6tDDoYIxWvMLTdKpjFkc1B","7vrJn5hDSXRmdXoR30KgF1","4loQgPwJHocL3dFwLfjb1J","3VvA1wSxukMLsvXoXtlwWx","7Bk0uXKk1uPT0XuQbpFzvs","5YYW3yRktprLRr47WK219Y","4PEfJZpVjdclfzZ9XO8uDw"],"TH":["2pn8dNVSpYnAtlKFC8Q0DJ","7MAibcTli4IisCtbHKrGMh","2dHoVW9AxJVSRebPRyV2aA","6GDI4Y8fOsptYwSW2iIUbe","4CTgPJbgNQ031q8HzhTtq2","5sXuqzLmT1z6Gnf3S2TzSz","19CoWVqDyUbiqxoyMf4HkJ","2vA7CHG08LDzeMDAuPnUQg","1RVYucT3tc32YzRDsP30t3","0AGhwXsWpVOwjHY5yf4dtD"],"TR":["3VT8hOC5vuDXBsHrR53WFh","10n66m41IGjA2ZulKPK7Ew","2huQiKGkgUfp4WjnVRSobL","7ng3MkDXpSUVFQEhN6vtqG","3XeMdSHi48X0XsDHckDhIM","4jq1WK3fiUU2SOhZ0iaMP1","5KvWAPJDBNXzy5l1bywB7x","2qmdgQun2BbLmIRsQsedER","7LGuxwQ3PzCxtinavcMlew","4KhTyJ1cJeHaY4ZS2u3e6A"],"TW":["2pn8dNVSpYnAtlKFC8Q0DJ","3OC84eKMxRJ4x0Hcwl9i4i","1Ytgo9ipdlTsf6wlg6sXf3","2dHoVW9AxJVSRebPRyV2aA","7MAibcTli4IisCtbHKrGMh","0O7O4sssbFxoNoB4QRGra1","69zgyr5HVKdInjeKpq1qHa","4u4NyuceXP7Uzh7XFJKCr1","5cU1O9P0EDA0rPkPDykhIm","4RewTiGEGoO7FWNZUmp1f4"],"UA":["3VT8hOC5vuDXBsHrR53WFh","4KiFqaxjnmVm0gyIPIRRgH","12Kknh5NqqAukiyevjDQkT","1ngGGsWzGONyiOlxdXRDr7","3HHVtWGKwhMwjUfsQGztzt","6f3Slt0GbA2bPZlz0aIFXN","1GOiMxQXZUzjzH0Sxpck0B","79i617mqpQLwUs3WTokYX9","6PAPPKv7XPCqPEG95UaOFa","4KfmruShP5zOi9hYjM76e6"],"UY":["1Crj1zkRMpsEjb9NOR6Zof","7I8L3vYCLThw2FDrE6LuzE","5YYW3yRktprLRr47WK219Y","1xK1Gg9SxG8fy2Ya373oqb","2XIc1pqjXV3Cr2BQUGNBck","6EHrppRT1Uj4cyShAujxFu","3VvA1wSxukMLsvXoXtlwWx","7vrJn5hDSXRmdXoR30KgF1","2TksvaRivgAEj780DgRB73","079Ey5uxL04AKPQgVQwx5h"],"VN":["2pn8dNVSpYnAtlKFC8Q0DJ","2dHoVW9AxJVSRebPRyV2aA","3wGx3gYPjECKZazGNuPEX2","17iGUekw5nFt5mIRJcUm3R","6rVaOdWvFaNyVVXda0NPJy","7MAibcTli4IisCtbHKrGMh","6IAqflHsPVm4EpYghXauX7","2f8Ew6sB7KHlTiH9NTLvVM","7wkX67ruxr3x2GFz6vyIX9","1fh5Sf3fFESFOS8D82RQiI"],"ZA":["3aQem4jVGdhtg116TmJnHz","6f3Slt0GbA2bPZlz0aIFXN","65OVbaJR5O1RmwOQx0875b","3FAJ6O0NOHQV8Mc5Ri6ENp","7MAibcTli4IisCtbHKrGMh","60ynsPSSKe6O3sfwRnIBRf","7lPN2DXiMsVn7XUKtOW1CS","2H1hYPeKgIQAp439cx7GsX","4FRW5Nza1Ym91BGV4nFWXI","5Kskr9LcNYa0tpt5f0ZEJx"]}